[{"bookId": "31532653", "title": "地球编年史（套装全七册）", "author": "撒迦利亚·西琴", "cover": "https://wfqqreader-1252317822.image.myqcloud.com/cover/653/31532653/s_31532653.jpg", "bookUrl": "https://weread.qq.com/web/appreader/1b2322e071e1266d1b27965"}, {"bookId": "25445341", "title": "道德经", "author": "老子", "cover": "https://wfqqreader-1252317822.image.myqcloud.com/cover/341/25445341/s_25445341.jpg", "bookUrl": "https://weread.qq.com/web/appreader/e7d32910718443dde7d8d46"}, {"bookId": "25445395", "title": "易经", "author": "周鹏鹏", "cover": "https://wfqqreader-1252317822.image.myqcloud.com/cover/395/25445395/s_25445395.jpg", "bookUrl": "https://weread.qq.com/web/appreader/2f7329f0718444132f71170"}, {"bookId": "31231952", "title": "历史学十二讲（增订本）", "author": "安托万·普罗斯特", "cover": "https://wfqqreader-1252317822.image.myqcloud.com/cover/952/31231952/s_31231952.jpg", "bookUrl": "https://weread.qq.com/web/appreader/7f83259071dc8fd07f89ab8"}, {"bookId": "814416", "title": "脂砚斋评石头记（全集）", "author": "曹雪芹 脂砚斋评", "cover": "https://wfqqreader-1252317822.image.myqcloud.com/cover/416/814416/s_814416.jpg", "bookUrl": "https://weread.qq.com/web/appreader/5ff325605c6d505ffe56991"}, {"bookId": "25445341", "title": "道德经", "author": "老子", "cover": "https://wfqqreader-1252317822.image.myqcloud.com/cover/341/25445341/s_25445341.jpg", "bookUrl": "https://weread.qq.com/web/appreader/e7d32910718443dde7d8d46"}, {"bookId": "839176", "title": "易中天中华史·第一部：先秦（套装共6册）", "author": "易中天", "cover": "https://wfqqreader-1252317822.image.myqcloud.com/cover/176/839176/s_839176.jpg", "bookUrl": "https://weread.qq.com/web/appreader/67732eb05cce08677ca6ed8"}, {"bookId": "839178", "title": "易中天中华史·第三部：隋唐（4册）", "author": "易中天", "cover": "https://wfqqreader-1252317822.image.myqcloud.com/cover/178/839178/s_839178.jpg", "bookUrl": "https://weread.qq.com/web/appreader/e67329b05cce0ae6737d538"}, {"bookId": "815123", "title": "曾国藩家书", "author": "曾国藩", "cover": "https://wfqqreader-1252317822.image.myqcloud.com/cover/123/815123/s_815123.jpg", "bookUrl": "https://weread.qq.com/web/appreader/566323505c7013566201ddc"}, {"bookId": "25445395", "title": "易经", "author": "周鹏鹏", "cover": "https://wfqqreader-1252317822.image.myqcloud.com/cover/395/25445395/s_25445395.jpg", "bookUrl": "https://weread.qq.com/web/appreader/2f7329f0718444132f71170"}, {"bookId": "26314563", "title": "万古江河", "author": "许倬云", "cover": "https://wfqqreader-1252317822.image.myqcloud.com/cover/563/26314563/s_26314563.jpg", "bookUrl": "https://weread.qq.com/web/appreader/bad3259071918743bad1ec8"}, {"bookId": "839177", "title": "易中天中华史·第二部：秦汉魏晋南北朝（套装共6册）", "author": "易中天", "cover": "https://wfqqreader-1252317822.image.myqcloud.com/cover/177/839177/s_839177.jpg", "bookUrl": "https://weread.qq.com/web/appreader/f1e327d05cce09f1eb6a815"}, {"bookId": "847437", "title": "金刚经·心经·四十二章经·六祖坛经（国学网原版点注，杨增文等点校）", "author": "鸠摩罗什译等原著 杨增文等点校", "cover": "https://wfqqreader-1252317822.image.myqcloud.com/cover/437/847437/s_847437.jpg", "bookUrl": "https://weread.qq.com/web/appreader/60932bd05cee4d609facdc7"}, {"bookId": "277539", "title": "黄帝内经", "author": "苏晶 袁世宏导读", "cover": "https://wfqqreader-1252317822.image.myqcloud.com/cover/539/277539/s_277539.jpg", "bookUrl": "https://weread.qq.com/web/appreader/8b532720543c238b5f93625"}, {"bookId": "837602", "title": "世说新语（精装典藏本）", "author": "刘义庆编撰", "cover": "https://wfqqreader-1252317822.image.myqcloud.com/cover/602/837602/s_837602.jpg", "bookUrl": "https://weread.qq.com/web/appreader/889324f05cc7e28899a2ad1"}, {"bookId": "815127", "title": "古文观止（全2册）", "author": "吴楚材 吴调候编选", "cover": "https://wfqqreader-1252317822.image.myqcloud.com/cover/127/815127/s_815127.jpg", "bookUrl": "https://weread.qq.com/web/appreader/40332f005c7017403a3255c"}, {"bookId": "918332", "title": "唐朝穿越指南：长安及各地人民生活手册（新版）", "author": "森林鹿", "cover": "https://wfqqreader-1252317822.image.myqcloud.com/cover/332/918332/s_918332.jpg", "bookUrl": "https://weread.qq.com/web/appreader/ed1323205e033ced1eb312a"}, {"bookId": "837605", "title": "智囊全集（精装典藏本）", "author": "冯梦龙编著", "cover": "https://wfqqreader-1252317822.image.myqcloud.com/cover/605/837605/s_837605.jpg", "bookUrl": "https://weread.qq.com/web/appreader/a9532a605cc7e5a9585e6e6"}, {"bookId": "720461", "title": "楚辞（精装典藏本）", "author": "屈原", "cover": "https://wfqqreader-1252317822.image.myqcloud.com/cover/461/720461/s_720461.jpg", "bookUrl": "https://weread.qq.com/web/appreader/b8e32e405afe4db8e201555"}, {"bookId": "924187", "title": "说文解字全鉴（珍藏版）", "author": "许慎", "cover": "https://wfqqreader-1252317822.image.myqcloud.com/cover/187/924187/s_924187.jpg", "bookUrl": "https://weread.qq.com/web/appreader/c8832a205e1a1bc88c499b8"}, {"bookId": "23523074", "title": "国史大纲（全2册）", "author": "钱穆", "cover": "https://wfqqreader-1252317822.image.myqcloud.com/cover/74/23523074/s_23523074.jpg", "bookUrl": "https://weread.qq.com/web/appreader/427326807166ef024271b86"}, {"bookId": "814931", "title": "三国志（上）", "author": "陈寿", "cover": "https://wfqqreader-1252317822.image.myqcloud.com/cover/931/814931/s_814931.jpg", "bookUrl": "https://weread.qq.com/web/appreader/6eb322305c6f536ebbfb1f0"}, {"bookId": "846253", "title": "三十六计", "author": "佚名著 赵中媛译注", "cover": "https://wfqqreader-1252317822.image.myqcloud.com/cover/253/846253/s_846253.jpg", "bookUrl": "https://weread.qq.com/web/appreader/07b326205ce9ad07b340eae"}, {"bookId": "26079432", "title": "六祖坛经", "author": "惠能著 李明注释", "cover": "https://wfqqreader-1252317822.image.myqcloud.com/cover/432/26079432/s_26079432.jpg", "bookUrl": "https://weread.qq.com/web/appreader/9e032020718df0c89e03b38"}, {"bookId": "838856", "title": "孙子兵法", "author": "孙武", "cover": "https://wfqqreader-1252317822.image.myqcloud.com/cover/856/838856/s_838856.jpg", "bookUrl": "https://weread.qq.com/web/appreader/f00329505cccc8f002688c1"}, {"bookId": "29793518", "title": "三国志", "author": "陈寿 裴松之", "cover": "https://wfqqreader-1252317822.image.myqcloud.com/cover/518/29793518/s_29793518.jpg", "bookUrl": "https://weread.qq.com/web/appreader/a11324a071c69ceea11aa97"}, {"bookId": "26631437", "title": "資治通鑑·繁體橫排版（胡三省注）294卷全", "author": "鄒寰宇 胡三省輯注 司馬光編集", "cover": "https://wfqqreader-1252317822.image.myqcloud.com/cover/437/26631437/s_26631437.jpg", "bookUrl": "https://weread.qq.com/web/appreader/f093266071965d0df09f8de"}, {"bookId": "333170", "title": "天下第一奇书：智囊大全集（白话译本）", "author": "冯梦龙", "cover": "https://wfqqreader-1252317822.image.myqcloud.com/cover/170/333170/s_333170.jpg", "bookUrl": "https://weread.qq.com/web/appreader/6e5327605515726e5f1a6df"}, {"bookId": "847436", "title": "金刚经·心经（国学网原版点注，杨增文、徐俊点校）", "author": "鸠摩罗什译等原著 杨增文 徐俊点校", "cover": "https://wfqqreader-1252317822.image.myqcloud.com/cover/436/847436/s_847436.jpg", "bookUrl": "https://weread.qq.com/web/appreader/13d324c05cee4c13df3cd8a"}, {"bookId": "918044", "title": "庄子全鉴（耀世典藏版）（国学今读系列）", "author": "庄子著 芳园主编", "cover": "https://wfqqreader-1252317822.image.myqcloud.com/cover/44/918044/s_918044.jpg", "bookUrl": "https://weread.qq.com/web/appreader/5b3328405e021c5b3e0efba"}, {"bookId": "26079564", "title": "唐诗三百首（注解本）", "author": "蘅塘退士编 管又清注解", "cover": "https://wfqqreader-1252317822.image.myqcloud.com/cover/564/26079564/s_26079564.jpg", "bookUrl": "https://weread.qq.com/web/appreader/911329e0718df14c9116086"}, {"bookId": "533399", "title": "山海经", "author": "佚名", "cover": "https://wfqqreader-1252317822.image.myqcloud.com/cover/399/533399/s_533399.jpg", "bookUrl": "https://weread.qq.com/web/appreader/6e732b905823976e73f70c4"}, {"bookId": "791689", "title": "论语·中庸·大学", "author": "孔子", "cover": "https://wfqqreader-1252317822.image.myqcloud.com/cover/689/791689/s_791689.jpg", "bookUrl": "https://weread.qq.com/web/appreader/b3132cc05c1489b31b965ca"}, {"bookId": "31532653", "title": "地球编年史（套装全七册）", "author": "撒迦利亚·西琴", "cover": "https://wfqqreader-1252317822.image.myqcloud.com/cover/653/31532653/s_31532653.jpg", "bookUrl": "https://weread.qq.com/web/appreader/1b2322e071e1266d1b27965"}, {"bookId": "820033", "title": "陶庵梦忆", "author": "张岱", "cover": "https://wfqqreader-1252317822.image.myqcloud.com/cover/33/820033/s_820033.jpg", "bookUrl": "https://weread.qq.com/web/appreader/3fe325b05c83413fe5df430"}, {"bookId": "791690", "title": "笑林广记", "author": "游戏主人", "cover": "https://wfqqreader-1252317822.image.myqcloud.com/cover/690/791690/s_791690.jpg", "bookUrl": "https://weread.qq.com/web/appreader/89032a305c148a890d8f911"}, {"bookId": "25445345", "title": "文心雕龙", "author": "刘勰", "cover": "https://wfqqreader-1252317822.image.myqcloud.com/cover/345/25445345/s_25445345.jpg", "bookUrl": "https://weread.qq.com/web/appreader/a0332b30718443e1a036270"}, {"bookId": "561300", "title": "二十四史", "author": "金开诚", "cover": "https://wfqqreader-1252317822.image.myqcloud.com/cover/300/561300/s_561300.jpg", "bookUrl": "https://weread.qq.com/web/appreader/7aa325305890947aa1adba0"}, {"bookId": "840990", "title": "赫逊河畔谈中国历史（精装版）", "author": "黄仁宇", "cover": "https://wfqqreader-1252317822.image.myqcloud.com/cover/990/840990/s_840990.jpg", "bookUrl": "https://weread.qq.com/web/appreader/50d321c05cd51e50d501ac4"}, {"bookId": "813293", "title": "彩图全解资治通鉴（彩图精装）", "author": "司马光", "cover": "https://wfqqreader-1252317822.image.myqcloud.com/cover/293/813293/s_813293.jpg", "bookUrl": "https://weread.qq.com/web/appreader/b7e32d405c68edb7e662284"}, {"bookId": "26079438", "title": "论语（古典名著普及文库）", "author": "孔子著 杨伯峻 杨逢彬注译 杨柳岸导读", "cover": "https://wfqqreader-1252317822.image.myqcloud.com/cover/438/26079438/s_26079438.jpg", "bookUrl": "https://weread.qq.com/web/appreader/a55325f0718df0cea554f19"}, {"bookId": "601437", "title": "三言二拍（全本珍藏版全5卷）", "author": "冯梦龙 凌濛初", "cover": "https://wfqqreader-1252317822.image.myqcloud.com/cover/437/601437/s_601437.jpg", "bookUrl": "https://weread.qq.com/web/appreader/a3332d00592d5da3370a286"}, {"bookId": "25445418", "title": "礼记", "author": "戴圣", "cover": "https://wfqqreader-1252317822.image.myqcloud.com/cover/418/25445418/s_25445418.jpg", "bookUrl": "https://weread.qq.com/web/appreader/732327d07184442a732e430"}, {"bookId": "820966", "title": "三国志（下）", "author": "陈寿", "cover": "https://wfqqreader-1252317822.image.myqcloud.com/cover/966/820966/s_820966.jpg", "bookUrl": "https://weread.qq.com/web/appreader/cf7328905c86e6cf70172b0"}, {"bookId": "918034", "title": "四书五经全鉴（耀世典藏版）（国学今读系列）", "author": "芳园", "cover": "https://wfqqreader-1252317822.image.myqcloud.com/cover/34/918034/s_918034.jpg", "bookUrl": "https://weread.qq.com/web/appreader/7ff32d805e02127ff42b348"}, {"bookId": "277540", "title": "中信国学大典·六祖坛经", "author": "净因法师导读及译注", "cover": "https://wfqqreader-1252317822.image.myqcloud.com/cover/540/277540/s_277540.jpg", "bookUrl": "https://weread.qq.com/web/appreader/81832a90543c24818557178"}, {"bookId": "927227", "title": "唐浩明评点曾国藩家书", "author": "唐浩明", "cover": "https://wfqqreader-1252317822.image.myqcloud.com/cover/227/927227/s_927227.jpg", "bookUrl": "https://weread.qq.com/web/appreader/c4432a105e25fbc44415b43"}, {"bookId": "27561571", "title": "周易", "author": "王辉编译", "cover": "https://wfqqreader-1252317822.image.myqcloud.com/cover/571/27561571/s_27561571.jpg", "bookUrl": "https://weread.qq.com/web/appreader/3cb32c9071a48e633cbfba3"}, {"bookId": "934881", "title": "易中天中华史：铁血蒙元", "author": "易中天", "cover": "https://wfqqreader-1252317822.image.myqcloud.com/cover/881/934881/s_934881.jpg", "bookUrl": "https://weread.qq.com/web/appreader/c0a32a605e43e1c0af65787"}, {"bookId": "837601", "title": "东坡志林（精装典藏本）", "author": "苏轼", "cover": "https://wfqqreader-1252317822.image.myqcloud.com/cover/601/837601/s_837601.jpg", "bookUrl": "https://weread.qq.com/web/appreader/a8d32a205cc7e1a8d464c68"}, {"bookId": "132765", "title": "伤寒杂病论", "author": "张仲景", "cover": "https://wfqqreader-1252317822.image.myqcloud.com/cover/765/132765/s_132765.jpg", "bookUrl": "https://weread.qq.com/web/appreader/9e232f0052069d9e29e0acd"}, {"bookId": "837601", "title": "东坡志林（精装典藏本）", "author": "苏轼", "cover": "https://wfqqreader-1252317822.image.myqcloud.com/cover/601/837601/s_837601.jpg", "bookUrl": "https://weread.qq.com/web/appreader/a8d32a205cc7e1a8d464c68"}, {"bookId": "25445339", "title": "大学·中庸", "author": "曾参 子思", "cover": "https://wfqqreader-1252317822.image.myqcloud.com/cover/339/25445339/s_25445339.jpg", "bookUrl": "https://weread.qq.com/web/appreader/95632ca0718443db9564b70"}, {"bookId": "29490548", "title": "东京梦华录", "author": "孟元老著 李秀萍注释", "cover": "https://wfqqreader-1252317822.image.myqcloud.com/cover/548/29490548/s_29490548.jpg", "bookUrl": "https://weread.qq.com/web/appreader/c6332e5071c1fd74c635f06"}, {"bookId": "25445347", "title": "鬼谷子", "author": "鬼谷子", "cover": "https://wfqqreader-1252317822.image.myqcloud.com/cover/347/25445347/s_25445347.jpg", "bookUrl": "https://weread.qq.com/web/appreader/56c32740718443e356c181c"}, {"bookId": "798518", "title": "诗经三百首大师导读", "author": "华夏国学书院", "cover": "https://wfqqreader-1252317822.image.myqcloud.com/cover/518/798518/s_798518.jpg", "bookUrl": "https://weread.qq.com/web/appreader/57b32c705c2f3657bf85bac"}, {"bookId": "26079495", "title": "儒林外史（古典文学阅读无障碍本）", "author": "吴敬梓", "cover": "https://wfqqreader-1252317822.image.myqcloud.com/cover/495/26079495/s_26079495.jpg", "bookUrl": "https://weread.qq.com/web/appreader/fea322f0718df107fea223d"}, {"bookId": "25507333", "title": "哈佛极简中国史：从文明起源到20世纪（修订珍藏版）", "author": "阿尔伯特·克雷格", "cover": "https://wfqqreader-1252317822.image.myqcloud.com/cover/333/25507333/s_25507333.jpg", "bookUrl": "https://weread.qq.com/web/appreader/7a032b70718536057a0f25e"}, {"bookId": "26777432", "title": "半小时喵星哲学史", "author": "胖乐胖乐", "cover": "https://wfqqreader-1252317822.image.myqcloud.com/cover/432/26777432/s_26777432.jpg", "bookUrl": "https://weread.qq.com/web/appreader/25d327207198975825dd117"}, {"bookId": "131875", "title": "庄子", "author": "庄子", "cover": "https://wfqqreader-1252317822.image.myqcloud.com/cover/875/131875/s_131875.jpg", "bookUrl": "https://weread.qq.com/web/appreader/db932390520323db9b1c794"}, {"bookId": "26079495", "title": "儒林外史（古典文学阅读无障碍本）", "author": "吴敬梓", "cover": "https://wfqqreader-1252317822.image.myqcloud.com/cover/495/26079495/s_26079495.jpg", "bookUrl": "https://weread.qq.com/web/appreader/fea322f0718df107fea223d"}, {"bookId": "131875", "title": "庄子", "author": "庄子", "cover": "https://wfqqreader-1252317822.image.myqcloud.com/cover/875/131875/s_131875.jpg", "bookUrl": "https://weread.qq.com/web/appreader/db932390520323db9b1c794"}, {"bookId": "24952462", "title": "论语", "author": "孔子", "cover": "https://wfqqreader-1252317822.image.myqcloud.com/cover/462/24952462/s_24952462.jpg", "bookUrl": "https://weread.qq.com/web/appreader/79d323a0717cbe8e79dc1e5"}, {"bookId": "25445414", "title": "智囊", "author": "冯梦龙", "cover": "https://wfqqreader-1252317822.image.myqcloud.com/cover/414/25445414/s_25445414.jpg", "bookUrl": "https://weread.qq.com/web/appreader/b5b320f071844426b5b3fe1"}, {"bookId": "25445333", "title": "黄帝内经", "author": "张凤娇", "cover": "https://wfqqreader-1252317822.image.myqcloud.com/cover/333/25445333/s_25445333.jpg", "bookUrl": "https://weread.qq.com/web/appreader/5e232c20718443d55e2b9e6"}, {"bookId": "26078982", "title": "庄子", "author": "庄周", "cover": "https://wfqqreader-1252317822.image.myqcloud.com/cover/982/26078982/s_26078982.jpg", "bookUrl": "https://weread.qq.com/web/appreader/c5732860718def06c574d84"}, {"bookId": "25445410", "title": "格言联璧", "author": "金缨", "cover": "https://wfqqreader-1252317822.image.myqcloud.com/cover/410/25445410/s_25445410.jpg", "bookUrl": "https://weread.qq.com/web/appreader/b2b323f071844422b2b0a26"}, {"bookId": "846837", "title": "荀子全鉴（典藏版）", "author": "荀子著 孙红颖解译", "cover": "https://wfqqreader-1252317822.image.myqcloud.com/cover/837/846837/s_846837.jpg", "bookUrl": "https://weread.qq.com/web/appreader/eff326a05cebf5effbb86c9"}, {"bookId": "927228", "title": "唐浩明评点曾国藩语录", "author": "唐浩明", "cover": "https://wfqqreader-1252317822.image.myqcloud.com/cover/228/927228/s_927228.jpg", "bookUrl": "https://weread.qq.com/web/appreader/ef732e405e25fcef70b7753"}, {"bookId": "22247795", "title": "历史（2018全新详注修订本）", "author": "希罗多德", "cover": "https://wfqqreader-1252317822.image.myqcloud.com/cover/795/22247795/s_22247795.jpg", "bookUrl": "https://weread.qq.com/web/appreader/4ef32140715379734ef5f31"}, {"bookId": "838848", "title": "三字经·百家姓·千字文·弟子规", "author": "王应麟等", "cover": "https://wfqqreader-1252317822.image.myqcloud.com/cover/848/838848/s_838848.jpg", "bookUrl": "https://weread.qq.com/web/appreader/d4c32bf05cccc0d4cf83fb5"}, {"bookId": "29979116", "title": "华杉讲透《资治通鉴》3", "author": "华杉", "cover": "https://wfqqreader-1252317822.image.myqcloud.com/cover/116/29979116/s_29979116.jpg", "bookUrl": "https://weread.qq.com/web/appreader/b6e32a6071c971ecb6eb022"}, {"bookId": "846848", "title": "阅微草堂笔记全鉴（典藏版）", "author": "纪昀", "cover": "https://wfqqreader-1252317822.image.myqcloud.com/cover/848/846848/s_846848.jpg", "bookUrl": "https://weread.qq.com/web/appreader/9a1326505cec009a1727d32"}, {"bookId": "220517", "title": "史记（最爱读国学书系）", "author": "刘洪仁 苏静", "cover": "https://wfqqreader-1252317822.image.myqcloud.com/cover/517/220517/s_220517.jpg", "bookUrl": "https://weread.qq.com/web/appreader/ac132250535d65ac14782e5"}, {"bookId": "803889", "title": "人间词话", "author": "王国维", "cover": "https://wfqqreader-1252317822.image.myqcloud.com/cover/889/803889/s_803889.jpg", "bookUrl": "https://weread.qq.com/web/appreader/3b1321e05c44313b1c91ddf"}, {"bookId": "917983", "title": "论语·中庸·大学（耀世典藏版）（国学今读系列）", "author": "孔子等著 芳园主编", "cover": "https://wfqqreader-1252317822.image.myqcloud.com/cover/983/917983/s_917983.jpg", "bookUrl": "https://weread.qq.com/web/appreader/37732e305e01df377b64565"}, {"bookId": "27216086", "title": "坤道：中国女人的修养", "author": "曾仕强", "cover": "https://wfqqreader-1252317822.image.myqcloud.com/cover/86/27216086/s_27216086.jpg", "bookUrl": "https://weread.qq.com/web/appreader/94032770719f48d69402599"}, {"bookId": "132766", "title": "黄帝内经", "author": "庾岭劳人", "cover": "https://wfqqreader-1252317822.image.myqcloud.com/cover/766/132766/s_132766.jpg", "bookUrl": "https://weread.qq.com/web/appreader/0723261052069e072119466"}, {"bookId": "846848", "title": "阅微草堂笔记全鉴（典藏版）", "author": "纪昀", "cover": "https://wfqqreader-1252317822.image.myqcloud.com/cover/848/846848/s_846848.jpg", "bookUrl": "https://weread.qq.com/web/appreader/9a1326505cec009a1727d32"}, {"bookId": "26767629", "title": "菜根谭+围炉夜话+小窗幽记", "author": "洪应明 王永彬 陈继儒", "cover": "https://wfqqreader-1252317822.image.myqcloud.com/cover/629/26767629/s_26767629.jpg", "bookUrl": "https://weread.qq.com/web/appreader/b2b32be07198710db2b3c38"}, {"bookId": "619201", "title": "山海经（中华国学经典）", "author": "袁堂欣 谢志强主编", "cover": "https://wfqqreader-1252317822.image.myqcloud.com/cover/201/619201/s_619201.jpg", "bookUrl": "https://weread.qq.com/web/appreader/68c324905972c168c27f616"}, {"bookId": "813354", "title": "彩图全解菜根谭（彩图精装）", "author": "洪应明 思履", "cover": "https://wfqqreader-1252317822.image.myqcloud.com/cover/354/813354/s_813354.jpg", "bookUrl": "https://weread.qq.com/web/appreader/3a6327505c692a3a68e302a"}, {"bookId": "927229", "title": "唐浩明评点曾国藩日记", "author": "唐浩明", "cover": "https://wfqqreader-1252317822.image.myqcloud.com/cover/229/927229/s_927229.jpg", "bookUrl": "https://weread.qq.com/web/appreader/6ca32c605e25fd6ca2615b2"}, {"bookId": "25670912", "title": "春秋大义：中国传统语境下的皇权与学术", "author": "熊逸", "cover": "https://wfqqreader-1252317822.image.myqcloud.com/cover/912/25670912/s_25670912.jpg", "bookUrl": "https://weread.qq.com/web/appreader/f5b328a07187b500f5b5568"}, {"bookId": "25445391", "title": "三国志", "author": "陈寿", "cover": "https://wfqqreader-1252317822.image.myqcloud.com/cover/391/25445391/s_25445391.jpg", "bookUrl": "https://weread.qq.com/web/appreader/4c532e107184440f4c57753"}, {"bookId": "926018", "title": "两晋：风流总被雨打风吹去", "author": "刘勃", "cover": "https://wfqqreader-1252317822.image.myqcloud.com/cover/18/926018/s_926018.jpg", "bookUrl": "https://weread.qq.com/web/appreader/a5732d705e2142a57994105"}, {"bookId": "619122", "title": "六韬·三略（中华国学经典）", "author": "袁堂欣 谢志强主编", "cover": "https://wfqqreader-1252317822.image.myqcloud.com/cover/122/619122/s_619122.jpg", "bookUrl": "https://weread.qq.com/web/appreader/a1032320597272a1065cf5a"}, {"bookId": "921501", "title": "唐朝定居指南（新版）", "author": "森林鹿", "cover": "https://wfqqreader-1252317822.image.myqcloud.com/cover/501/921501/s_921501.jpg", "bookUrl": "https://weread.qq.com/web/appreader/5e732b905e0f9d5e792fd2f"}, {"bookId": "684725", "title": "园冶", "author": "计成", "cover": "https://wfqqreader-1252317822.image.myqcloud.com/cover/725/684725/s_684725.jpg", "bookUrl": "https://weread.qq.com/web/appreader/4c3325c05a72b54c3eec0ee"}, {"bookId": "619122", "title": "六韬·三略（中华国学经典）", "author": "袁堂欣 谢志强主编", "cover": "https://wfqqreader-1252317822.image.myqcloud.com/cover/122/619122/s_619122.jpg", "bookUrl": "https://weread.qq.com/web/appreader/a1032320597272a1065cf5a"}, {"bookId": "846845", "title": "左传全鉴（典藏版）", "author": "左丘明著 蔡践解译", "cover": "https://wfqqreader-1252317822.image.myqcloud.com/cover/845/846845/s_846845.jpg", "bookUrl": "https://weread.qq.com/web/appreader/d8f329f05cebfdd8f3478a5"}, {"bookId": "857258", "title": "王阳明全集（权威版38卷+增补2卷 真正全集）", "author": "王阳明", "cover": "https://wfqqreader-1252317822.image.myqcloud.com/cover/258/857258/s_857258.jpg", "bookUrl": "https://weread.qq.com/web/appreader/f2632e705d14aaf2659ee88"}, {"bookId": "840198", "title": "大宋革新", "author": "易中天", "cover": "https://wfqqreader-1252317822.image.myqcloud.com/cover/198/840198/s_840198.jpg", "bookUrl": "https://weread.qq.com/web/appreader/4be324605cd2064be47abea"}, {"bookId": "854811", "title": "易中天中华史：王安石变法", "author": "易中天", "cover": "https://wfqqreader-1252317822.image.myqcloud.com/cover/811/854811/s_854811.jpg", "bookUrl": "https://weread.qq.com/web/appreader/7f932ae05d0b1b7f9783f76"}, {"bookId": "25205927", "title": "中华史纲", "author": "李定一", "cover": "https://wfqqreader-1252317822.image.myqcloud.com/cover/927/25205927/s_25205927.jpg", "bookUrl": "https://weread.qq.com/web/appreader/7a032b6071809ca77a03c78"}, {"bookId": "25499069", "title": "新家庭书架升级版：资治通鉴", "author": "司马光", "cover": "https://wfqqreader-1252317822.image.myqcloud.com/cover/69/25499069/s_25499069.jpg", "bookUrl": "https://weread.qq.com/web/appreader/24332fd0718515bd2431be9"}, {"bookId": "29758688", "title": "中国通史", "author": "吕思勉", "cover": "https://wfqqreader-1252317822.image.myqcloud.com/cover/688/29758688/s_29758688.jpg", "bookUrl": "https://weread.qq.com/web/appreader/4e532cb071c614e04e54ada"}, {"bookId": "24019448", "title": "南北战争三百年：中国4—6世纪的军事与政权", "author": "李硕", "cover": "https://wfqqreader-1252317822.image.myqcloud.com/cover/448/24019448/s_24019448.jpg", "bookUrl": "https://weread.qq.com/web/appreader/b9232b90716e81f8b92f48f"}, {"bookId": "855271", "title": "历史的个性：兵家", "author": "扶栏客", "cover": "https://wfqqreader-1252317822.image.myqcloud.com/cover/271/855271/s_855271.jpg", "bookUrl": "https://weread.qq.com/web/appreader/369324f05d0ce736932670a"}, {"bookId": "25499069", "title": "新家庭书架升级版：资治通鉴", "author": "司马光", "cover": "https://wfqqreader-1252317822.image.myqcloud.com/cover/69/25499069/s_25499069.jpg", "bookUrl": "https://weread.qq.com/web/appreader/24332fd0718515bd2431be9"}, {"bookId": "27325733", "title": "76号特工总部", "author": "马振犊 陆军", "cover": "https://wfqqreader-1252317822.image.myqcloud.com/cover/733/27325733/s_27325733.jpg", "bookUrl": "https://weread.qq.com/web/appreader/1bc32a5071a0f5251bc3b0b"}, {"bookId": "855271", "title": "历史的个性：兵家", "author": "扶栏客", "cover": "https://wfqqreader-1252317822.image.myqcloud.com/cover/271/855271/s_855271.jpg", "bookUrl": "https://weread.qq.com/web/appreader/369324f05d0ce736932670a"}, {"bookId": "24019448", "title": "南北战争三百年：中国4—6世纪的军事与政权", "author": "李硕", "cover": "https://wfqqreader-1252317822.image.myqcloud.com/cover/448/24019448/s_24019448.jpg", "bookUrl": "https://weread.qq.com/web/appreader/b9232b90716e81f8b92f48f"}, {"bookId": "27216086", "title": "坤道：中国女人的修养", "author": "曾仕强", "cover": "https://wfqqreader-1252317822.image.myqcloud.com/cover/86/27216086/s_27216086.jpg", "bookUrl": "https://weread.qq.com/web/appreader/94032770719f48d69402599"}, {"bookId": "672222", "title": "《传习录》明隆庆六年初刻版", "author": "王阳明", "cover": "https://wfqqreader-1252317822.image.myqcloud.com/cover/222/672222/s_672222.jpg", "bookUrl": "https://weread.qq.com/web/appreader/7e4321905a41de7e490a780"}, {"bookId": "846843", "title": "汉书全鉴（典藏版）", "author": "班固著 东篱子解译", "cover": "https://wfqqreader-1252317822.image.myqcloud.com/cover/843/846843/s_846843.jpg", "bookUrl": "https://weread.qq.com/web/appreader/c79321305cebfbc79bc03f0"}, {"bookId": "730941", "title": "北大历史课", "author": "程门立雪编著", "cover": "https://wfqqreader-1252317822.image.myqcloud.com/cover/941/730941/s_730941.jpg", "bookUrl": "https://weread.qq.com/web/appreader/17c325805b273d17c76b063"}, {"bookId": "855272", "title": "历史的个性：江湖", "author": "扶栏客", "cover": "https://wfqqreader-1252317822.image.myqcloud.com/cover/272/855272/s_855272.jpg", "bookUrl": "https://weread.qq.com/web/appreader/5b3329905d0ce85b30d201c"}, {"bookId": "846843", "title": "汉书全鉴（典藏版）", "author": "班固著 东篱子解译", "cover": "https://wfqqreader-1252317822.image.myqcloud.com/cover/843/846843/s_846843.jpg", "bookUrl": "https://weread.qq.com/web/appreader/c79321305cebfbc79bc03f0"}, {"bookId": "672222", "title": "《传习录》明隆庆六年初刻版", "author": "王阳明", "cover": "https://wfqqreader-1252317822.image.myqcloud.com/cover/222/672222/s_672222.jpg", "bookUrl": "https://weread.qq.com/web/appreader/7e4321905a41de7e490a780"}, {"bookId": "26079382", "title": "封神演义（古典文学阅读无障碍本）", "author": "许仲琳", "cover": "https://wfqqreader-1252317822.image.myqcloud.com/cover/382/26079382/s_26079382.jpg", "bookUrl": "https://weread.qq.com/web/appreader/78b32750718df09678b5bc4"}, {"bookId": "242923", "title": "袁天罡与推背图", "author": "党忠义", "cover": "https://wfqqreader-1252317822.image.myqcloud.com/cover/923/242923/s_242923.jpg", "bookUrl": "https://weread.qq.com/web/appreader/95d3288053b4eb95db4358f"}, {"bookId": "846254", "title": "山海经", "author": "傅硕译注", "cover": "https://wfqqreader-1252317822.image.myqcloud.com/cover/254/846254/s_846254.jpg", "bookUrl": "https://weread.qq.com/web/appreader/800321505ce9ae800ca9534"}, {"bookId": "242923", "title": "袁天罡与推背图", "author": "党忠义", "cover": "https://wfqqreader-1252317822.image.myqcloud.com/cover/923/242923/s_242923.jpg", "bookUrl": "https://weread.qq.com/web/appreader/95d3288053b4eb95db4358f"}, {"bookId": "30883918", "title": "中国通史简编", "author": "范文澜", "cover": "https://wfqqreader-1252317822.image.myqcloud.com/cover/918/30883918/s_30883918.jpg", "bookUrl": "https://weread.qq.com/web/appreader/7f232f2071d7404e7f2979e"}, {"bookId": "23665516", "title": "民粹主义大爆炸", "author": "约翰·朱迪斯", "cover": "https://wfqqreader-1252317822.image.myqcloud.com/cover/516/23665516/s_23665516.jpg", "bookUrl": "https://weread.qq.com/web/appreader/4dc32a0071691b6c4dcb7d3"}, {"bookId": "933001", "title": "雅尔塔：改变世界格局的八天", "author": "沙希利·浦洛基", "cover": "https://wfqqreader-1252317822.image.myqcloud.com/cover/1/933001/s_933001.jpg", "bookUrl": "https://weread.qq.com/web/appreader/eb5321405e3c89eb5ee2624"}, {"bookId": "31130785", "title": "中国通史：精装插图本", "author": "吕思勉", "cover": "https://wfqqreader-1252317822.image.myqcloud.com/cover/785/31130785/s_31130785.jpg", "bookUrl": "https://weread.qq.com/web/appreader/0cd3264071db04a10cd06e6"}, {"bookId": "31282929", "title": "熊逸：纸上的精神旅行（春秋大义+正义从哪里来）", "author": "熊逸", "cover": "https://wfqqreader-1252317822.image.myqcloud.com/cover/929/31282929/s_31282929.jpg", "bookUrl": "https://weread.qq.com/web/appreader/4d532e8071dd56f14d54c60"}, {"bookId": "27325755", "title": "武田信玄：风林山火（上下全集）", "author": "新田次郎", "cover": "https://wfqqreader-1252317822.image.myqcloud.com/cover/755/27325755/s_27325755.jpg", "bookUrl": "https://weread.qq.com/web/appreader/827327e071a0f53b827e358"}, {"bookId": "846835", "title": "墨子全鉴（典藏版）", "author": "墨子编撰 东篱子解译", "cover": "https://wfqqreader-1252317822.image.myqcloud.com/cover/835/846835/s_846835.jpg", "bookUrl": "https://weread.qq.com/web/appreader/77b320705cebf377b0bb529"}, {"bookId": "522375", "title": "金匮要略（四库全书）", "author": "虞舜 点校", "cover": "https://wfqqreader-1252317822.image.myqcloud.com/cover/375/522375/s_522375.jpg", "bookUrl": "https://weread.qq.com/web/appreader/c0e327a057f887c0e5d950f"}, {"bookId": "813307", "title": "古文观止全解（彩图精装）", "author": "吴楚材 吴调侯 思履", "cover": "https://wfqqreader-1252317822.image.myqcloud.com/cover/307/813307/s_813307.jpg", "bookUrl": "https://weread.qq.com/web/appreader/cc2329805c68fbcc28834f0"}, {"bookId": "924090", "title": "三国志全鉴（珍藏版）", "author": "陈寿", "cover": "https://wfqqreader-1252317822.image.myqcloud.com/cover/90/924090/s_924090.jpg", "bookUrl": "https://weread.qq.com/web/appreader/50632a505e19ba5068dd53e"}, {"bookId": "857421", "title": "权力的智慧：冰与火的中国历史定律", "author": "宗承灏", "cover": "https://wfqqreader-1252317822.image.myqcloud.com/cover/421/857421/s_857421.jpg", "bookUrl": "https://weread.qq.com/web/appreader/06332b705d154d063424923"}, {"bookId": "619217", "title": "文心雕龙（中华国学经典）", "author": "袁堂欣 谢志强主编", "cover": "https://wfqqreader-1252317822.image.myqcloud.com/cover/217/619217/s_619217.jpg", "bookUrl": "https://weread.qq.com/web/appreader/de932f805972d1de933d68a"}, {"bookId": "31231952", "title": "历史学十二讲（增订本）", "author": "安托万·普罗斯特", "cover": "https://wfqqreader-1252317822.image.myqcloud.com/cover/952/31231952/s_31231952.jpg", "bookUrl": "https://weread.qq.com/web/appreader/7f83259071dc8fd07f89ab8"}, {"bookId": "26079501", "title": "商君书（古典名著白文本）", "author": "商鞅", "cover": "https://wfqqreader-1252317822.image.myqcloud.com/cover/501/26079501/s_26079501.jpg", "bookUrl": "https://weread.qq.com/web/appreader/c10324c0718df10dc1051ca"}, {"bookId": "798520", "title": "唐诗三百首大师导读", "author": "华夏国学书院", "cover": "https://wfqqreader-1252317822.image.myqcloud.com/cover/520/798520/s_798520.jpg", "bookUrl": "https://weread.qq.com/web/appreader/7d932c405c2f387d9c2b83f"}, {"bookId": "22247793", "title": "治史三书（增订版）", "author": "严耕望", "cover": "https://wfqqreader-1252317822.image.myqcloud.com/cover/793/22247793/s_22247793.jpg", "bookUrl": "https://weread.qq.com/web/appreader/22432ee071537971224662f"}, {"bookId": "31231952", "title": "历史学十二讲（增订本）", "author": "安托万·普罗斯特", "cover": "https://wfqqreader-1252317822.image.myqcloud.com/cover/952/31231952/s_31231952.jpg", "bookUrl": "https://weread.qq.com/web/appreader/7f83259071dc8fd07f89ab8"}, {"bookId": "26079501", "title": "商君书（古典名著白文本）", "author": "商鞅", "cover": "https://wfqqreader-1252317822.image.myqcloud.com/cover/501/26079501/s_26079501.jpg", "bookUrl": "https://weread.qq.com/web/appreader/c10324c0718df10dc1051ca"}, {"bookId": "29793565", "title": "左传（全二册）", "author": "左丘明 杜预集解", "cover": "https://wfqqreader-1252317822.image.myqcloud.com/cover/565/29793565/s_29793565.jpg", "bookUrl": "https://weread.qq.com/web/appreader/b95321c071c69d1db95b45c"}, {"bookId": "837603", "title": "六韬 三略（精装典藏本）", "author": "张亮译注", "cover": "https://wfqqreader-1252317822.image.myqcloud.com/cover/603/837603/s_837603.jpg", "bookUrl": "https://weread.qq.com/web/appreader/eff321c05cc7e3eff79d58a"}, {"bookId": "798520", "title": "唐诗三百首大师导读", "author": "华夏国学书院", "cover": "https://wfqqreader-1252317822.image.myqcloud.com/cover/520/798520/s_798520.jpg", "bookUrl": "https://weread.qq.com/web/appreader/7d932c405c2f387d9c2b83f"}, {"bookId": "857421", "title": "权力的智慧：冰与火的中国历史定律", "author": "宗承灏", "cover": "https://wfqqreader-1252317822.image.myqcloud.com/cover/421/857421/s_857421.jpg", "bookUrl": "https://weread.qq.com/web/appreader/06332b705d154d063424923"}, {"bookId": "924090", "title": "三国志全鉴（珍藏版）", "author": "陈寿", "cover": "https://wfqqreader-1252317822.image.myqcloud.com/cover/90/924090/s_924090.jpg", "bookUrl": "https://weread.qq.com/web/appreader/50632a505e19ba5068dd53e"}, {"bookId": "909202", "title": "群书治要（精装典藏版）", "author": "魏徴等编撰", "cover": "https://wfqqreader-1252317822.image.myqcloud.com/cover/202/909202/s_909202.jpg", "bookUrl": "https://weread.qq.com/web/appreader/82e32cb05ddf9282e1195df"}, {"bookId": "847307", "title": "唐诗三百首", "author": "蘅塘退士选编", "cover": "https://wfqqreader-1252317822.image.myqcloud.com/cover/307/847307/s_847307.jpg", "bookUrl": "https://weread.qq.com/web/appreader/c36327605cedcbc36a332fb"}, {"bookId": "29490610", "title": "资治通鉴", "author": "司马光", "cover": "https://wfqqreader-1252317822.image.myqcloud.com/cover/610/29490610/s_29490610.jpg", "bookUrl": "https://weread.qq.com/web/appreader/d3d32cb071c1fdb2d3d2a60"}, {"bookId": "29490610", "title": "资治通鉴", "author": "司马光", "cover": "https://wfqqreader-1252317822.image.myqcloud.com/cover/610/29490610/s_29490610.jpg", "bookUrl": "https://weread.qq.com/web/appreader/d3d32cb071c1fdb2d3d2a60"}, {"bookId": "26079485", "title": "七侠五义（古典文学阅读无障碍本）", "author": "石玉昆", "cover": "https://wfqqreader-1252317822.image.myqcloud.com/cover/485/26079485/s_26079485.jpg", "bookUrl": "https://weread.qq.com/web/appreader/f5e32b00718df0fdf5e232e"}, {"bookId": "846838", "title": "了凡四训全鉴（典藏版）", "author": "袁黄著 东篱子解译", "cover": "https://wfqqreader-1252317822.image.myqcloud.com/cover/838/846838/s_846838.jpg", "bookUrl": "https://weread.qq.com/web/appreader/ec232de05cebf6ec2dc2714"}, {"bookId": "26991750", "title": "陶渊明诗文选集", "author": "陶渊明 杨义 邵明明评注", "cover": "https://wfqqreader-1252317822.image.myqcloud.com/cover/750/26991750/s_26991750.jpg", "bookUrl": "https://weread.qq.com/web/appreader/485324f0719bdc864857dff"}, {"bookId": "846838", "title": "了凡四训全鉴（典藏版）", "author": "袁黄著 东篱子解译", "cover": "https://wfqqreader-1252317822.image.myqcloud.com/cover/838/846838/s_846838.jpg", "bookUrl": "https://weread.qq.com/web/appreader/ec232de05cebf6ec2dc2714"}, {"bookId": "25445387", "title": "孙子兵法", "author": "孙武", "cover": "https://wfqqreader-1252317822.image.myqcloud.com/cover/387/25445387/s_25445387.jpg", "bookUrl": "https://weread.qq.com/web/appreader/b43329607184440bb439dbb"}, {"bookId": "911344", "title": "三天读懂四书五经（图文典藏版）", "author": "中教翰盟编著", "cover": "https://wfqqreader-1252317822.image.myqcloud.com/cover/344/911344/s_911344.jpg", "bookUrl": "https://weread.qq.com/web/appreader/cb2323b05de7f0cb28c73ff"}, {"bookId": "846840", "title": "淮南子全鉴（典藏版）", "author": "刘安著 迟东篱子解译", "cover": "https://wfqqreader-1252317822.image.myqcloud.com/cover/840/846840/s_846840.jpg", "bookUrl": "https://weread.qq.com/web/appreader/9e232db05cebf89e28652b7"}, {"bookId": "26297828", "title": "智囊全鉴（典藏诵读版）", "author": "冯梦龙", "cover": "https://wfqqreader-1252317822.image.myqcloud.com/cover/828/26297828/s_26297828.jpg", "bookUrl": "https://weread.qq.com/web/appreader/c8d32f40719145e4c8d178c"}, {"bookId": "913492", "title": "国学常识", "author": "曹伯韩", "cover": "https://wfqqreader-1252317822.image.myqcloud.com/cover/492/913492/s_913492.jpg", "bookUrl": "https://weread.qq.com/web/appreader/14832a605df0541487836b8"}, {"bookId": "610040", "title": "战国策（中国古代经典集粹）", "author": "刘向", "cover": "https://wfqqreader-1252317822.image.myqcloud.com/cover/40/610040/s_610040.jpg", "bookUrl": "https://weread.qq.com/web/appreader/21c32180594ef821cdcb12a"}, {"bookId": "924261", "title": "后汉书全鉴", "author": "范晔", "cover": "https://wfqqreader-1252317822.image.myqcloud.com/cover/261/924261/s_924261.jpg", "bookUrl": "https://weread.qq.com/web/appreader/e84329d05e1a65e840ede71"}]
