[{"bookId": "27405538", "title": "装在口袋里的爸爸（套装16册）（装在口袋里的爸爸）", "author": "杨鹏", "cover": "https://wfqqreader-1252317822.image.myqcloud.com/cover/538/27405538/s_27405538.jpg", "bookUrl": "https://weread.qq.com/web/appreader/40d32f7071a22ce240d5ec4"}, {"bookId": "23652048", "title": "365夜睡前故事", "author": "钟锐", "cover": "https://wfqqreader-1252317822.image.myqcloud.com/cover/48/23652048/s_23652048.jpg", "bookUrl": "https://weread.qq.com/web/appreader/a8032be07168e6d0a80834f"}, {"bookId": "650956", "title": "格林童话", "author": "格林兄弟", "cover": "https://wfqqreader-1252317822.image.myqcloud.com/cover/956/650956/s_650956.jpg", "bookUrl": "https://weread.qq.com/web/appreader/7803217059eecc7807bcca6"}, {"bookId": "917542", "title": "孩子们的诗", "author": "果麦", "cover": "https://wfqqreader-1252317822.image.myqcloud.com/cover/542/917542/s_917542.jpg", "bookUrl": "https://weread.qq.com/web/appreader/c6e32cc05e0026c6e5bf3d9"}, {"bookId": "933828", "title": "动物小说大王沈石溪·品藏书系（新版全套28册）", "author": "沈石溪", "cover": "https://wfqqreader-1252317822.image.myqcloud.com/cover/828/933828/s_933828.jpg", "bookUrl": "https://weread.qq.com/web/appreader/94c32c405e3fc494c07f1b1"}, {"bookId": "839248", "title": "宝葫芦的秘密", "author": "张天翼", "cover": "https://wfqqreader-1252317822.image.myqcloud.com/cover/248/839248/s_839248.jpg", "bookUrl": "https://weread.qq.com/web/appreader/233323c05cce5023318f037"}, {"bookId": "25499119", "title": "曹文轩小说阅读与鉴赏：青铜葵花", "author": "曹文轩", "cover": "https://wfqqreader-1252317822.image.myqcloud.com/cover/119/25499119/s_25499119.jpg", "bookUrl": "https://weread.qq.com/web/appreader/85932470718515ef8592884"}, {"bookId": "916892", "title": "影响孩子一生的101个童话故事", "author": "童心", "cover": "https://wfqqreader-1252317822.image.myqcloud.com/cover/892/916892/s_916892.jpg", "bookUrl": "https://weread.qq.com/web/appreader/61832fe05dfd9c6188f9d7f"}, {"bookId": "908201", "title": "郑渊洁十二生肖童话（全12册）", "author": "郑渊洁", "cover": "https://wfqqreader-1252317822.image.myqcloud.com/cover/201/908201/s_908201.jpg", "bookUrl": "https://weread.qq.com/web/appreader/68f322205ddba968fd3bc63"}, {"bookId": "165467", "title": "安徒生童话（中小学生必读丛书）", "author": "安徒生", "cover": "https://wfqqreader-1252317822.image.myqcloud.com/cover/467/165467/s_165467.jpg", "bookUrl": "https://weread.qq.com/web/appreader/b6a3260052865bb6ac2a86b"}, {"bookId": "699613", "title": "伊索寓言", "author": "伊索", "cover": "https://wfqqreader-1252317822.image.myqcloud.com/cover/613/699613/s_699613.jpg", "bookUrl": "https://weread.qq.com/web/appreader/548329905aacdd5487b04d7"}, {"bookId": "699613", "title": "伊索寓言", "author": "伊索", "cover": "https://wfqqreader-1252317822.image.myqcloud.com/cover/613/699613/s_699613.jpg", "bookUrl": "https://weread.qq.com/web/appreader/548329905aacdd5487b04d7"}, {"bookId": "25323630", "title": "西南联大行思录", "author": "张曼菱", "cover": "https://wfqqreader-1252317822.image.myqcloud.com/cover/630/25323630/s_25323630.jpg", "bookUrl": "https://weread.qq.com/web/appreader/83732b307182686e837a42b"}, {"bookId": "926154", "title": "爱丽丝梦游仙境", "author": "刘易斯·卡罗尔", "cover": "https://wfqqreader-1252317822.image.myqcloud.com/cover/154/926154/s_926154.jpg", "bookUrl": "https://weread.qq.com/web/appreader/76532ba05e21ca7657e8463"}, {"bookId": "148745", "title": "爱的教育", "author": "亚米契斯", "cover": "https://wfqqreader-1252317822.image.myqcloud.com/cover/745/148745/s_148745.jpg", "bookUrl": "https://weread.qq.com/web/appreader/f3232930524509f32dfd85a"}, {"bookId": "22860204", "title": "格林童话（全集）", "author": "格林兄弟", "cover": "https://wfqqreader-1252317822.image.myqcloud.com/cover/204/22860204/s_22860204.jpg", "bookUrl": "https://weread.qq.com/web/appreader/53a322d0715cd1ac53a9c2c"}, {"bookId": "839246", "title": "稻草人", "author": "叶圣陶", "cover": "https://wfqqreader-1252317822.image.myqcloud.com/cover/246/839246/s_839246.jpg", "bookUrl": "https://weread.qq.com/web/appreader/b0e324105cce4eb0e1f7bd7"}, {"bookId": "531056", "title": "狼王梦", "author": "沈石溪", "cover": "https://wfqqreader-1252317822.image.myqcloud.com/cover/56/531056/s_531056.jpg", "bookUrl": "https://weread.qq.com/web/appreader/2fc32d00581a702fce82eaa"}, {"bookId": "916688", "title": "小王子：中英法对照（彩绘珍藏版）", "author": "圣埃克絮佩里", "cover": "https://wfqqreader-1252317822.image.myqcloud.com/cover/688/916688/s_916688.jpg", "bookUrl": "https://weread.qq.com/web/appreader/4c732c505dfcd04c768da28"}, {"bookId": "627148", "title": "格林童话精选大全", "author": "格林著 雅瑟编译", "cover": "https://wfqqreader-1252317822.image.myqcloud.com/cover/148/627148/s_627148.jpg", "bookUrl": "https://weread.qq.com/web/appreader/add32c305991ccadd297044"}, {"bookId": "779666", "title": "郑渊洁四大名传（全集）", "author": "郑渊洁", "cover": "https://wfqqreader-1252317822.image.myqcloud.com/cover/666/779666/s_779666.jpg", "bookUrl": "https://weread.qq.com/web/appreader/a3732dd05be592a373f323f"}, {"bookId": "24026529", "title": "三国演义（少年儿童版）", "author": "罗贯中 行人 刘文忠", "cover": "https://wfqqreader-1252317822.image.myqcloud.com/cover/529/24026529/s_24026529.jpg", "bookUrl": "https://weread.qq.com/web/appreader/cf632680716e9da1cf6a8a0"}, {"bookId": "23065329", "title": "做人与处世", "author": "季羡林", "cover": "https://wfqqreader-1252317822.image.myqcloud.com/cover/329/23065329/s_23065329.jpg", "bookUrl": "https://weread.qq.com/web/appreader/b1832100715ff2f1b18c039"}, {"bookId": "25658238", "title": "骑鹅旅行记", "author": "塞尔玛·拉格洛芙", "cover": "https://wfqqreader-1252317822.image.myqcloud.com/cover/238/25658238/s_25658238.jpg", "bookUrl": "https://weread.qq.com/web/appreader/0e832a207187837e0e879cd"}, {"bookId": "779662", "title": "舒克贝塔传", "author": "郑渊洁", "cover": "https://wfqqreader-1252317822.image.myqcloud.com/cover/662/779662/s_779662.jpg", "bookUrl": "https://weread.qq.com/web/appreader/27432c905be58e27419a1d0"}, {"bookId": "779665", "title": "皮皮鲁传", "author": "郑渊洁", "cover": "https://wfqqreader-1252317822.image.myqcloud.com/cover/665/779665/s_779665.jpg", "bookUrl": "https://weread.qq.com/web/appreader/4ae323805be5914aee0534a"}, {"bookId": "159193", "title": "绿野仙踪", "author": "弗兰克·鲍姆", "cover": "https://wfqqreader-1252317822.image.myqcloud.com/cover/193/159193/s_159193.jpg", "bookUrl": "https://weread.qq.com/web/appreader/173328a0526dd91736ad263"}, {"bookId": "832632", "title": "皮皮鲁和魔方大厦", "author": "郑渊洁", "cover": "https://wfqqreader-1252317822.image.myqcloud.com/cover/632/832632/s_832632.jpg", "bookUrl": "https://weread.qq.com/web/appreader/94632ed05cb478946fb5c91"}, {"bookId": "457577", "title": "千字文（国学启蒙书系列）", "author": "韩震", "cover": "https://wfqqreader-1252317822.image.myqcloud.com/cover/577/457577/s_457577.jpg", "bookUrl": "https://weread.qq.com/web/appreader/a913215056fb69a9117c712"}, {"bookId": "916813", "title": "小熊温尼365夜睡前故事：春", "author": "彭凡", "cover": "https://wfqqreader-1252317822.image.myqcloud.com/cover/813/916813/s_916813.jpg", "bookUrl": "https://weread.qq.com/web/appreader/00332e305dfd4d003b5a36d"}, {"bookId": "933455", "title": "装在口袋里的爸爸：超级透视眼", "author": "杨鹏", "cover": "https://wfqqreader-1252317822.image.myqcloud.com/cover/455/933455/s_933455.jpg", "bookUrl": "https://weread.qq.com/web/appreader/73732a905e3e4f737800b1d"}, {"bookId": "23303587", "title": "安徒生童话故事集", "author": "安徒生", "cover": "https://wfqqreader-1252317822.image.myqcloud.com/cover/587/23303587/s_23303587.jpg", "bookUrl": "https://weread.qq.com/web/appreader/02e32880716395a302eaf3e"}, {"bookId": "26087720", "title": "给孩子的唐诗课", "author": "六神磊磊", "cover": "https://wfqqreader-1252317822.image.myqcloud.com/cover/720/26087720/s_26087720.jpg", "bookUrl": "https://weread.qq.com/web/appreader/12032240718e1128120cb6c"}, {"bookId": "26254954", "title": "给孩子看世界名画", "author": "果麦", "cover": "https://wfqqreader-1252317822.image.myqcloud.com/cover/954/26254954/s_26254954.jpg", "bookUrl": "https://weread.qq.com/web/appreader/8553284071909e6a8559402"}, {"bookId": "933454", "title": "装在口袋里的爸爸：隐身小侠", "author": "杨鹏", "cover": "https://wfqqreader-1252317822.image.myqcloud.com/cover/454/933454/s_933454.jpg", "bookUrl": "https://weread.qq.com/web/appreader/78132e305e3e4e781523de1"}, {"bookId": "24284327", "title": "一千零一夜（全册）", "author": "阿拉伯民间故事", "cover": "https://wfqqreader-1252317822.image.myqcloud.com/cover/327/24284327/s_24284327.jpg", "bookUrl": "https://weread.qq.com/web/appreader/c43329d071728ca7c43ca02"}, {"bookId": "832635", "title": "皮皮鲁遥控老师", "author": "郑渊洁", "cover": "https://wfqqreader-1252317822.image.myqcloud.com/cover/635/832635/s_832635.jpg", "bookUrl": "https://weread.qq.com/web/appreader/d3f321c05cb47bd3f25c18b"}, {"bookId": "832629", "title": "皮皮鲁和309暗室", "author": "郑渊洁", "cover": "https://wfqqreader-1252317822.image.myqcloud.com/cover/629/832629/s_832629.jpg", "bookUrl": "https://weread.qq.com/web/appreader/c2732fe05cb475c27798f38"}, {"bookId": "613736", "title": "快乐王子", "author": "王尔德", "cover": "https://wfqqreader-1252317822.image.myqcloud.com/cover/736/613736/s_613736.jpg", "bookUrl": "https://weread.qq.com/web/appreader/a8732860595d68a87910773"}, {"bookId": "933441", "title": "装在口袋里的爸爸：聪明饭", "author": "杨鹏", "cover": "https://wfqqreader-1252317822.image.myqcloud.com/cover/441/933441/s_933441.jpg", "bookUrl": "https://weread.qq.com/web/appreader/d32324205e3e41d329942da"}, {"bookId": "844394", "title": "神笔马良", "author": "洪汛涛", "cover": "https://wfqqreader-1252317822.image.myqcloud.com/cover/394/844394/s_844394.jpg", "bookUrl": "https://weread.qq.com/web/appreader/8f832ff05ce26a8f80dd760"}, {"bookId": "854814", "title": "十亿分之一的文明", "author": "刘慈欣", "cover": "https://wfqqreader-1252317822.image.myqcloud.com/cover/814/854814/s_854814.jpg", "bookUrl": "https://weread.qq.com/web/appreader/ebf325b05d0b1eebff807af"}, {"bookId": "25499109", "title": "曹文轩小说阅读与鉴赏：草房子", "author": "曹文轩", "cover": "https://wfqqreader-1252317822.image.myqcloud.com/cover/109/25499109/s_25499109.jpg", "bookUrl": "https://weread.qq.com/web/appreader/9da326c0718515e59da8742"}, {"bookId": "854818", "title": "孤独的进化者", "author": "刘慈欣", "cover": "https://wfqqreader-1252317822.image.myqcloud.com/cover/818/854818/s_854818.jpg", "bookUrl": "https://weread.qq.com/web/appreader/16032c105d0b22160b40235"}, {"bookId": "908200", "title": "皮皮鲁的动物王国（全六册）", "author": "郑渊洁", "cover": "https://wfqqreader-1252317822.image.myqcloud.com/cover/200/908200/s_908200.jpg", "bookUrl": "https://weread.qq.com/web/appreader/89a322c05ddba889a8bdec8"}, {"bookId": "916896", "title": "影响孩子一生的101个智慧故事", "author": "童心", "cover": "https://wfqqreader-1252317822.image.myqcloud.com/cover/896/916896/s_916896.jpg", "bookUrl": "https://weread.qq.com/web/appreader/e6a32ab05dfda0e6a2f29db"}, {"bookId": "23768385", "title": "王尔德童话", "author": "王尔德", "cover": "https://wfqqreader-1252317822.image.myqcloud.com/cover/385/23768385/s_23768385.jpg", "bookUrl": "https://weread.qq.com/web/appreader/82032180716aad418205bbb"}, {"bookId": "23319429", "title": "海蒂（世界文学名著经典）", "author": "约翰娜·斯比丽", "cover": "https://wfqqreader-1252317822.image.myqcloud.com/cover/429/23319429/s_23319429.jpg", "bookUrl": "https://weread.qq.com/web/appreader/9a132b107163d3859a1e732"}, {"bookId": "846807", "title": "那些千古流传的经典名句", "author": "祁冰", "cover": "https://wfqqreader-1252317822.image.myqcloud.com/cover/807/846807/s_846807.jpg", "bookUrl": "https://weread.qq.com/web/appreader/2f3321b05cebd72f387948e"}, {"bookId": "699230", "title": "木偶奇遇记", "author": "卡洛·科洛迪", "cover": "https://wfqqreader-1252317822.image.myqcloud.com/cover/230/699230/s_699230.jpg", "bookUrl": "https://weread.qq.com/web/appreader/8f2323905aab5e8f2e7a0d7"}, {"bookId": "531307", "title": "第七条猎狗", "author": "沈石溪", "cover": "https://wfqqreader-1252317822.image.myqcloud.com/cover/307/531307/s_531307.jpg", "bookUrl": "https://weread.qq.com/web/appreader/70332a40581b6b7033b10fe"}, {"bookId": "832630", "title": "皮皮鲁和66宗罪", "author": "郑渊洁", "cover": "https://wfqqreader-1252317822.image.myqcloud.com/cover/630/832630/s_832630.jpg", "bookUrl": "https://weread.qq.com/web/appreader/98532ed05cb476985429568"}, {"bookId": "779664", "title": "鲁西西传", "author": "郑渊洁", "cover": "https://wfqqreader-1252317822.image.myqcloud.com/cover/664/779664/s_779664.jpg", "bookUrl": "https://weread.qq.com/web/appreader/1c5322805be5901c5a95362"}, {"bookId": "170338", "title": "3岁对了，一辈子就对了", "author": "陈素娟", "cover": "https://wfqqreader-1252317822.image.myqcloud.com/cover/338/170338/s_170338.jpg", "bookUrl": "https://weread.qq.com/web/appreader/8d432a905299628d47fa23d"}, {"bookId": "829267", "title": "尼尔斯骑鹅旅行记（美绘本）", "author": "塞尔玛·拉格罗夫 吴松林译", "cover": "https://wfqqreader-1252317822.image.myqcloud.com/cover/267/829267/s_829267.jpg", "bookUrl": "https://weread.qq.com/web/appreader/aca32fb05ca753aca42a67a"}, {"bookId": "908210", "title": "皮皮鲁和教室里的隐身人", "author": "郑渊洁", "cover": "https://wfqqreader-1252317822.image.myqcloud.com/cover/210/908210/s_908210.jpg", "bookUrl": "https://weread.qq.com/web/appreader/70a323b05ddbb270aa8b9e2"}, {"bookId": "839226", "title": "大林和小林", "author": "张天翼", "cover": "https://wfqqreader-1252317822.image.myqcloud.com/cover/226/839226/s_839226.jpg", "bookUrl": "https://weread.qq.com/web/appreader/1f332a405cce3a1f39c6bfe"}, {"bookId": "933452", "title": "装在口袋里的爸爸：时间魔表", "author": "杨鹏", "cover": "https://wfqqreader-1252317822.image.myqcloud.com/cover/452/933452/s_933452.jpg", "bookUrl": "https://weread.qq.com/web/appreader/21f321505e3e4c21f1567cd"}, {"bookId": "933452", "title": "装在口袋里的爸爸：时间魔表", "author": "杨鹏", "cover": "https://wfqqreader-1252317822.image.myqcloud.com/cover/452/933452/s_933452.jpg", "bookUrl": "https://weread.qq.com/web/appreader/21f321505e3e4c21f1567cd"}, {"bookId": "908209", "title": "皮皮鲁和大侦探乔麦皮", "author": "郑渊洁", "cover": "https://wfqqreader-1252317822.image.myqcloud.com/cover/209/908209/s_908209.jpg", "bookUrl": "https://weread.qq.com/web/appreader/f63328f05ddbb1f637991de"}, {"bookId": "856138", "title": "汤姆·索亚历险记（经典译林）", "author": "马克·吐温", "cover": "https://wfqqreader-1252317822.image.myqcloud.com/cover/138/856138/s_856138.jpg", "bookUrl": "https://weread.qq.com/web/appreader/c9e322e05d104ac9e01b49c"}, {"bookId": "933439", "title": "装在口袋里的爸爸：不会笑的插班生", "author": "杨鹏", "cover": "https://wfqqreader-1252317822.image.myqcloud.com/cover/439/933439/s_933439.jpg", "bookUrl": "https://weread.qq.com/web/appreader/fe5328605e3e3ffe5b95b42"}, {"bookId": "933448", "title": "装在口袋里的爸爸：我会七十二变", "author": "杨鹏", "cover": "https://wfqqreader-1252317822.image.myqcloud.com/cover/448/933448/s_933448.jpg", "bookUrl": "https://weread.qq.com/web/appreader/533322805e3e4853318b466"}, {"bookId": "933456", "title": "装在口袋里的爸爸：天气控制器", "author": "杨鹏", "cover": "https://wfqqreader-1252317822.image.myqcloud.com/cover/456/933456/s_933456.jpg", "bookUrl": "https://weread.qq.com/web/appreader/750328105e3e50750e3ad22"}, {"bookId": "933448", "title": "装在口袋里的爸爸：我会七十二变", "author": "杨鹏", "cover": "https://wfqqreader-1252317822.image.myqcloud.com/cover/448/933448/s_933448.jpg", "bookUrl": "https://weread.qq.com/web/appreader/533322805e3e4853318b466"}, {"bookId": "933439", "title": "装在口袋里的爸爸：不会笑的插班生", "author": "杨鹏", "cover": "https://wfqqreader-1252317822.image.myqcloud.com/cover/439/933439/s_933439.jpg", "bookUrl": "https://weread.qq.com/web/appreader/fe5328605e3e3ffe5b95b42"}, {"bookId": "24987281", "title": "中国神话故事集", "author": "朱大可主编", "cover": "https://wfqqreader-1252317822.image.myqcloud.com/cover/281/24987281/s_24987281.jpg", "bookUrl": "https://weread.qq.com/web/appreader/27b32380717d469127b7898"}, {"bookId": "908728", "title": "阿凡提的故事", "author": "赵世杰", "cover": "https://wfqqreader-1252317822.image.myqcloud.com/cover/728/908728/s_908728.jpg", "bookUrl": "https://weread.qq.com/web/appreader/cfb329c05dddb8cfb7c9da1"}, {"bookId": "854817", "title": "爱因斯坦赤道", "author": "刘慈欣", "cover": "https://wfqqreader-1252317822.image.myqcloud.com/cover/817/854817/s_854817.jpg", "bookUrl": "https://weread.qq.com/web/appreader/6bc329105d0b216bca659e3"}, {"bookId": "26407984", "title": "纳尼亚传奇（全集）", "author": "C.S.刘易斯", "cover": "https://wfqqreader-1252317822.image.myqcloud.com/cover/984/26407984/s_26407984.jpg", "bookUrl": "https://weread.qq.com/web/appreader/2de32c307192f4302de525e"}, {"bookId": "933451", "title": "装在口袋里的爸爸：神仙爸爸", "author": "杨鹏", "cover": "https://wfqqreader-1252317822.image.myqcloud.com/cover/451/933451/s_933451.jpg", "bookUrl": "https://weread.qq.com/web/appreader/38f328005e3e4b38ffbe3c6"}, {"bookId": "908206", "title": "皮皮鲁和魔鬼号列车", "author": "郑渊洁", "cover": "https://wfqqreader-1252317822.image.myqcloud.com/cover/206/908206/s_908206.jpg", "bookUrl": "https://weread.qq.com/web/appreader/477324105ddbae477cc3165"}, {"bookId": "531305", "title": "混血豺王", "author": "沈石溪", "cover": "https://wfqqreader-1252317822.image.myqcloud.com/cover/305/531305/s_531305.jpg", "bookUrl": "https://weread.qq.com/web/appreader/8ed32f30581b698edf37fdc"}, {"bookId": "910621", "title": "爱的教育（世界名著必读经典）", "author": "亚米契斯", "cover": "https://wfqqreader-1252317822.image.myqcloud.com/cover/621/910621/s_910621.jpg", "bookUrl": "https://weread.qq.com/web/appreader/61f326805de51d61f43c225"}, {"bookId": "933457", "title": "装在口袋里的爸爸：万能打印机", "author": "杨鹏", "cover": "https://wfqqreader-1252317822.image.myqcloud.com/cover/457/933457/s_933457.jpg", "bookUrl": "https://weread.qq.com/web/appreader/91f323a05e3e5191f64cf92"}, {"bookId": "24913525", "title": "绿野仙踪（英文版）", "author": "莱曼·弗兰克·鲍姆著 威廉·华莱士·丹斯诺绘", "cover": "https://wfqqreader-1252317822.image.myqcloud.com/cover/525/24913525/s_24913525.jpg", "bookUrl": "https://weread.qq.com/web/appreader/7b232550717c26757b29ebb"}, {"bookId": "650942", "title": "柳林风声", "author": "肯尼斯·格雷厄姆", "cover": "https://wfqqreader-1252317822.image.myqcloud.com/cover/942/650942/s_650942.jpg", "bookUrl": "https://weread.qq.com/web/appreader/76f3283059eebe76fa9a164"}, {"bookId": "933426", "title": "装在口袋里的爸爸：基因超人", "author": "杨鹏", "cover": "https://wfqqreader-1252317822.image.myqcloud.com/cover/426/933426/s_933426.jpg", "bookUrl": "https://weread.qq.com/web/appreader/c57325805e3e32c57b88bfe"}, {"bookId": "832631", "title": "皮皮鲁和幻影号", "author": "郑渊洁", "cover": "https://wfqqreader-1252317822.image.myqcloud.com/cover/631/832631/s_832631.jpg", "bookUrl": "https://weread.qq.com/web/appreader/7d032e705cb4777d0379cd9"}, {"bookId": "840954", "title": "怪老头儿", "author": "孙幼军", "cover": "https://wfqqreader-1252317822.image.myqcloud.com/cover/954/840954/s_840954.jpg", "bookUrl": "https://weread.qq.com/web/appreader/c40321505cd4fac40559397"}, {"bookId": "832628", "title": "皮皮鲁分身记", "author": "郑渊洁", "cover": "https://wfqqreader-1252317822.image.myqcloud.com/cover/628/832628/s_832628.jpg", "bookUrl": "https://weread.qq.com/web/appreader/43c326505cb47443c79e0b9"}, {"bookId": "832633", "title": "皮皮鲁送你100条命", "author": "郑渊洁", "cover": "https://wfqqreader-1252317822.image.myqcloud.com/cover/633/832633/s_832633.jpg", "bookUrl": "https://weread.qq.com/web/appreader/914327105cb4799144688fe"}, {"bookId": "23308800", "title": "中国寓言故事", "author": "曾凡跃", "cover": "https://wfqqreader-1252317822.image.myqcloud.com/cover/800/23308800/s_23308800.jpg", "bookUrl": "https://weread.qq.com/web/appreader/d32321e07163aa00d32b554"}, {"bookId": "23869148", "title": "美国少儿英语（英文彩色插图版）（第二辑·套装共3册）", "author": "威廉·H.爱尔森 卢娜·E.伦克尔", "cover": "https://wfqqreader-1252317822.image.myqcloud.com/cover/148/23869148/s_23869148.jpg", "bookUrl": "https://weread.qq.com/web/appreader/40632d30716c36dc406eb66"}, {"bookId": "832633", "title": "皮皮鲁送你100条命", "author": "郑渊洁", "cover": "https://wfqqreader-1252317822.image.myqcloud.com/cover/633/832633/s_832633.jpg", "bookUrl": "https://weread.qq.com/web/appreader/914327105cb4799144688fe"}, {"bookId": "29285968", "title": "日本的童话", "author": "小川未明等", "cover": "https://wfqqreader-1252317822.image.myqcloud.com/cover/968/29285968/s_29285968.jpg", "bookUrl": "https://weread.qq.com/web/appreader/08c32a5071bede5008ca1a4"}, {"bookId": "844484", "title": "星星和蒲公英（日本儿童文学大师系列）", "author": "金子美玲", "cover": "https://wfqqreader-1252317822.image.myqcloud.com/cover/484/844484/s_844484.jpg", "bookUrl": "https://weread.qq.com/web/appreader/039326505ce2c4039db0b4a"}, {"bookId": "23030829", "title": "校园三剑客·外星老师（经典版）", "author": "杨鹏", "cover": "https://wfqqreader-1252317822.image.myqcloud.com/cover/829/23030829/s_23030829.jpg", "bookUrl": "https://weread.qq.com/web/appreader/c1932e70715f6c2dc19b4c9"}, {"bookId": "933453", "title": "装在口袋里的爸爸：我是超人", "author": "杨鹏", "cover": "https://wfqqreader-1252317822.image.myqcloud.com/cover/453/933453/s_933453.jpg", "bookUrl": "https://weread.qq.com/web/appreader/403328605e3e4d403254bd6"}, {"bookId": "23308733", "title": "克雷洛夫寓言", "author": "克雷洛夫", "cover": "https://wfqqreader-1252317822.image.myqcloud.com/cover/733/23308733/s_23308733.jpg", "bookUrl": "https://weread.qq.com/web/appreader/e0932c907163a9bde0954c8"}, {"bookId": "839247", "title": "窃读记", "author": "林海音", "cover": "https://wfqqreader-1252317822.image.myqcloud.com/cover/247/839247/s_839247.jpg", "bookUrl": "https://weread.qq.com/web/appreader/8aa32ff05cce4f8aa0da9aa"}, {"bookId": "812685", "title": "彼得·潘", "author": "詹姆斯·马修·巴利", "cover": "https://wfqqreader-1252317822.image.myqcloud.com/cover/685/812685/s_812685.jpg", "bookUrl": "https://weread.qq.com/web/appreader/08f325d05c668d08f419bb1"}, {"bookId": "917769", "title": "父与子：汉英对照", "author": "卜劳恩著 李文昊编", "cover": "https://wfqqreader-1252317822.image.myqcloud.com/cover/769/917769/s_917769.jpg", "bookUrl": "https://weread.qq.com/web/appreader/2f832eb05e01092f8062d43"}, {"bookId": "832634", "title": "皮皮鲁压缩人生7天", "author": "郑渊洁", "cover": "https://wfqqreader-1252317822.image.myqcloud.com/cover/634/832634/s_832634.jpg", "bookUrl": "https://weread.qq.com/web/appreader/000326805cb47a00079e142"}, {"bookId": "933445", "title": "装在口袋里的爸爸：美梦制造机", "author": "杨鹏", "cover": "https://wfqqreader-1252317822.image.myqcloud.com/cover/445/933445/s_933445.jpg", "bookUrl": "https://weread.qq.com/web/appreader/6dc326f05e3e456dc2e4aba"}, {"bookId": "547741", "title": "讲给孩子最好听的故事", "author": "布歌恩特", "cover": "https://wfqqreader-1252317822.image.myqcloud.com/cover/741/547741/s_547741.jpg", "bookUrl": "https://weread.qq.com/web/appreader/06d32560585b9d06de7a2e7"}, {"bookId": "779663", "title": "大灰狼罗克传", "author": "郑渊洁", "cover": "https://wfqqreader-1252317822.image.myqcloud.com/cover/663/779663/s_779663.jpg", "bookUrl": "https://weread.qq.com/web/appreader/4a4329305be58f4a41b633a"}, {"bookId": "23303640", "title": "格林童话（全集）", "author": "格林兄弟", "cover": "https://wfqqreader-1252317822.image.myqcloud.com/cover/640/23303640/s_23303640.jpg", "bookUrl": "https://weread.qq.com/web/appreader/f81325c0716395d8f81aca9"}, {"bookId": "917550", "title": "汉字是画出来的", "author": "小象汉字", "cover": "https://wfqqreader-1252317822.image.myqcloud.com/cover/550/917550/s_917550.jpg", "bookUrl": "https://weread.qq.com/web/appreader/8f032c905e002e8f0ef5a69"}, {"bookId": "583497", "title": "世界儿童故事经典：亲情故事", "author": "宫方", "cover": "https://wfqqreader-1252317822.image.myqcloud.com/cover/497/583497/s_583497.jpg", "bookUrl": "https://weread.qq.com/web/appreader/9aa3245058e7499aa47cb2e"}, {"bookId": "531300", "title": "最后一头战象", "author": "沈石溪", "cover": "https://wfqqreader-1252317822.image.myqcloud.com/cover/300/531300/s_531300.jpg", "bookUrl": "https://weread.qq.com/web/appreader/4e432cc0581b644e468338e"}, {"bookId": "908202", "title": "皮皮鲁驯兔记", "author": "郑渊洁", "cover": "https://wfqqreader-1252317822.image.myqcloud.com/cover/202/908202/s_908202.jpg", "bookUrl": "https://weread.qq.com/web/appreader/c3c326605ddbaac3ce255f7"}, {"bookId": "829993", "title": "白雪公主（英文版）", "author": "格林", "cover": "https://wfqqreader-1252317822.image.myqcloud.com/cover/993/829993/s_829993.jpg", "bookUrl": "https://weread.qq.com/web/appreader/de8329405caa29de82b3cb7"}, {"bookId": "832028", "title": "夜莺与玫瑰（英汉对照图文典藏版）", "author": "王尔德 林徽因等译", "cover": "https://wfqqreader-1252317822.image.myqcloud.com/cover/28/832028/s_832028.jpg", "bookUrl": "https://weread.qq.com/web/appreader/b0f325005cb21cb0f089af6"}, {"bookId": "27248181", "title": "少年读史记系列（全5册）", "author": "张嘉骅", "cover": "https://wfqqreader-1252317822.image.myqcloud.com/cover/181/27248181/s_27248181.jpg", "bookUrl": "https://weread.qq.com/web/appreader/c4f32ef0719fc635c4f9127"}, {"bookId": "933425", "title": "装在口袋里的爸爸：点石成金", "author": "杨鹏", "cover": "https://wfqqreader-1252317822.image.myqcloud.com/cover/425/933425/s_933425.jpg", "bookUrl": "https://weread.qq.com/web/appreader/24b320805e3e3124bc459a8"}, {"bookId": "917769", "title": "父与子：汉英对照", "author": "卜劳恩著 李文昊编", "cover": "https://wfqqreader-1252317822.image.myqcloud.com/cover/769/917769/s_917769.jpg", "bookUrl": "https://weread.qq.com/web/appreader/2f832eb05e01092f8062d43"}, {"bookId": "933425", "title": "装在口袋里的爸爸：点石成金", "author": "杨鹏", "cover": "https://wfqqreader-1252317822.image.myqcloud.com/cover/425/933425/s_933425.jpg", "bookUrl": "https://weread.qq.com/web/appreader/24b320805e3e3124bc459a8"}, {"bookId": "908207", "title": "皮皮鲁和穿风衣的猫", "author": "郑渊洁", "cover": "https://wfqqreader-1252317822.image.myqcloud.com/cover/207/908207/s_908207.jpg", "bookUrl": "https://weread.qq.com/web/appreader/62132cc05ddbaf621728f22"}, {"bookId": "919652", "title": "寓言故事", "author": "王佳希", "cover": "https://wfqqreader-1252317822.image.myqcloud.com/cover/652/919652/s_919652.jpg", "bookUrl": "https://weread.qq.com/web/appreader/af632df05e0864af66ec97f"}, {"bookId": "934886", "title": "我的妈妈是精灵", "author": "陈丹燕", "cover": "https://wfqqreader-1252317822.image.myqcloud.com/cover/886/934886/s_934886.jpg", "bookUrl": "https://weread.qq.com/web/appreader/c76325405e43e6c76772f74"}, {"bookId": "23652046", "title": "365夜动物故事", "author": "钟锐", "cover": "https://wfqqreader-1252317822.image.myqcloud.com/cover/46/23652046/s_23652046.jpg", "bookUrl": "https://weread.qq.com/web/appreader/afa322b07168e6ceafa60f1"}, {"bookId": "933429", "title": "装在口袋里的爸爸：瞬移少年", "author": "杨鹏", "cover": "https://wfqqreader-1252317822.image.myqcloud.com/cover/429/933429/s_933429.jpg", "bookUrl": "https://weread.qq.com/web/appreader/dfe328b05e3e35dfe177636"}, {"bookId": "23030813", "title": "校园三剑客·神秘男孩（经典版）", "author": "杨鹏", "cover": "https://wfqqreader-1252317822.image.myqcloud.com/cover/813/23030813/s_23030813.jpg", "bookUrl": "https://weread.qq.com/web/appreader/a8732b40715f6c1da87377d"}, {"bookId": "23182383", "title": "小猪唏哩呼噜", "author": "孙幼军", "cover": "https://wfqqreader-1252317822.image.myqcloud.com/cover/383/23182383/s_23182383.jpg", "bookUrl": "https://weread.qq.com/web/appreader/8eb329e07161bc2f8eb37bf"}, {"bookId": "531306", "title": "残狼灰满", "author": "沈石溪", "cover": "https://wfqqreader-1252317822.image.myqcloud.com/cover/306/531306/s_531306.jpg", "bookUrl": "https://weread.qq.com/web/appreader/53032aa0581b6a53057b8cf"}, {"bookId": "916450", "title": "三字经", "author": "童心", "cover": "https://wfqqreader-1252317822.image.myqcloud.com/cover/450/916450/s_916450.jpg", "bookUrl": "https://weread.qq.com/web/appreader/f95323a05dfbe2f9548e350"}, {"bookId": "533397", "title": "双面猎犬", "author": "沈石溪", "cover": "https://wfqqreader-1252317822.image.myqcloud.com/cover/397/533397/s_533397.jpg", "bookUrl": "https://weread.qq.com/web/appreader/17532320582395175d09d90"}, {"bookId": "533397", "title": "双面猎犬", "author": "沈石溪", "cover": "https://wfqqreader-1252317822.image.myqcloud.com/cover/397/533397/s_533397.jpg", "bookUrl": "https://weread.qq.com/web/appreader/17532320582395175d09d90"}, {"bookId": "933446", "title": "装在口袋里的爸爸：魔药", "author": "杨鹏", "cover": "https://wfqqreader-1252317822.image.myqcloud.com/cover/446/933446/s_933446.jpg", "bookUrl": "https://weread.qq.com/web/appreader/4a432ff05e3e464a4a557d7"}, {"bookId": "916450", "title": "三字经", "author": "童心", "cover": "https://wfqqreader-1252317822.image.myqcloud.com/cover/450/916450/s_916450.jpg", "bookUrl": "https://weread.qq.com/web/appreader/f95323a05dfbe2f9548e350"}, {"bookId": "23182383", "title": "小猪唏哩呼噜", "author": "孙幼军", "cover": "https://wfqqreader-1252317822.image.myqcloud.com/cover/383/23182383/s_23182383.jpg", "bookUrl": "https://weread.qq.com/web/appreader/8eb329e07161bc2f8eb37bf"}, {"bookId": "531306", "title": "残狼灰满", "author": "沈石溪", "cover": "https://wfqqreader-1252317822.image.myqcloud.com/cover/306/531306/s_531306.jpg", "bookUrl": "https://weread.qq.com/web/appreader/53032aa0581b6a53057b8cf"}, {"bookId": "27562990", "title": "花猫三丫上房了", "author": "叶广芩", "cover": "https://wfqqreader-1252317822.image.myqcloud.com/cover/990/27562990/s_27562990.jpg", "bookUrl": "https://weread.qq.com/web/appreader/f5f322e071a493eef5fb24d"}, {"bookId": "23030813", "title": "校园三剑客·神秘男孩（经典版）", "author": "杨鹏", "cover": "https://wfqqreader-1252317822.image.myqcloud.com/cover/813/23030813/s_23030813.jpg", "bookUrl": "https://weread.qq.com/web/appreader/a8732b40715f6c1da87377d"}, {"bookId": "23182383", "title": "小猪唏哩呼噜", "author": "孙幼军", "cover": "https://wfqqreader-1252317822.image.myqcloud.com/cover/383/23182383/s_23182383.jpg", "bookUrl": "https://weread.qq.com/web/appreader/8eb329e07161bc2f8eb37bf"}, {"bookId": "933437", "title": "装在口袋里的爸爸：爸爸被盗版", "author": "杨鹏", "cover": "https://wfqqreader-1252317822.image.myqcloud.com/cover/437/933437/s_933437.jpg", "bookUrl": "https://weread.qq.com/web/appreader/25632f305e3e3d256aa594d"}, {"bookId": "531306", "title": "残狼灰满", "author": "沈石溪", "cover": "https://wfqqreader-1252317822.image.myqcloud.com/cover/306/531306/s_531306.jpg", "bookUrl": "https://weread.qq.com/web/appreader/53032aa0581b6a53057b8cf"}, {"bookId": "533397", "title": "双面猎犬", "author": "沈石溪", "cover": "https://wfqqreader-1252317822.image.myqcloud.com/cover/397/533397/s_533397.jpg", "bookUrl": "https://weread.qq.com/web/appreader/17532320582395175d09d90"}, {"bookId": "933433", "title": "装在口袋里的爸爸：神奇宝瓶", "author": "杨鹏", "cover": "https://wfqqreader-1252317822.image.myqcloud.com/cover/433/933433/s_933433.jpg", "bookUrl": "https://weread.qq.com/web/appreader/9a432f505e3e399a4d308e1"}, {"bookId": "831283", "title": "鼠王做寿", "author": "郑渊洁", "cover": "https://wfqqreader-1252317822.image.myqcloud.com/cover/283/831283/s_831283.jpg", "bookUrl": "https://weread.qq.com/web/appreader/838321505caf33838e5b2b9"}, {"bookId": "933424", "title": "装在口袋里的爸爸：颠倒沙漏", "author": "杨鹏", "cover": "https://wfqqreader-1252317822.image.myqcloud.com/cover/424/933424/s_933424.jpg", "bookUrl": "https://weread.qq.com/web/appreader/e5032d605e3e30e506f8ec7"}, {"bookId": "531308", "title": "红飘带狮王", "author": "沈石溪", "cover": "https://wfqqreader-1252317822.image.myqcloud.com/cover/308/531308/s_531308.jpg", "bookUrl": "https://weread.qq.com/web/appreader/3a732560581b6c3a76f8a14"}, {"bookId": "27009897", "title": "故宫怪兽谈（2019升级版，3册套装）", "author": "常怡", "cover": "https://wfqqreader-1252317822.image.myqcloud.com/cover/897/27009897/s_27009897.jpg", "bookUrl": "https://weread.qq.com/web/appreader/e5c32b20719c2369e5cbb89"}, {"bookId": "533395", "title": "雄狮去流浪", "author": "沈石溪", "cover": "https://wfqqreader-1252317822.image.myqcloud.com/cover/395/533395/s_533395.jpg", "bookUrl": "https://weread.qq.com/web/appreader/7e2328005823937e24a391f"}, {"bookId": "933830", "title": "刀疤豺母（动物小说大王沈石溪·品藏书系）", "author": "沈石溪", "cover": "https://wfqqreader-1252317822.image.myqcloud.com/cover/830/933830/s_933830.jpg", "bookUrl": "https://weread.qq.com/web/appreader/304328a05e3fc6304bbd1f1"}, {"bookId": "908208", "title": "皮皮鲁和复活的恐龙", "author": "郑渊洁", "cover": "https://wfqqreader-1252317822.image.myqcloud.com/cover/208/908208/s_908208.jpg", "bookUrl": "https://weread.qq.com/web/appreader/657329405ddbb0657a8fa46"}, {"bookId": "908204", "title": "皮皮鲁和流星暴雨", "author": "郑渊洁", "cover": "https://wfqqreader-1252317822.image.myqcloud.com/cover/204/908204/s_908204.jpg", "bookUrl": "https://weread.qq.com/web/appreader/7ae320405ddbac7ae3814a8"}, {"bookId": "933434", "title": "装在口袋里的爸爸：无敌戒指", "author": "杨鹏", "cover": "https://wfqqreader-1252317822.image.myqcloud.com/cover/434/933434/s_933434.jpg", "bookUrl": "https://weread.qq.com/web/appreader/166328305e3e3a166f3bbfe"}, {"bookId": "534462", "title": "兵猴传奇", "author": "沈石溪", "cover": "https://wfqqreader-1252317822.image.myqcloud.com/cover/462/534462/s_534462.jpg", "bookUrl": "https://weread.qq.com/web/appreader/05132d705827be051e0a8f9"}, {"bookId": "932119", "title": "安徒生童话（译文名著精选）", "author": "汉斯·安徒生", "cover": "https://wfqqreader-1252317822.image.myqcloud.com/cover/119/932119/s_932119.jpg", "bookUrl": "https://weread.qq.com/web/appreader/e54327b05e3917e542da6f5"}, {"bookId": "27195990", "title": "母豺火烧云（升级版）（动物小说大王沈石溪·品藏书系）", "author": "沈石溪", "cover": "https://wfqqreader-1252317822.image.myqcloud.com/cover/990/27195990/s_27195990.jpg", "bookUrl": "https://weread.qq.com/web/appreader/e4a32ab0719efa56e4ab9dc"}, {"bookId": "512983", "title": "陪伴孩子香甜入睡的108个好故事", "author": "张志伟编著", "cover": "https://wfqqreader-1252317822.image.myqcloud.com/cover/983/512983/s_512983.jpg", "bookUrl": "https://weread.qq.com/web/appreader/b17323b057d3d7b1748d61e"}, {"bookId": "933438", "title": "装在口袋里的爸爸：爸爸变小记", "author": "杨鹏", "cover": "https://wfqqreader-1252317822.image.myqcloud.com/cover/438/933438/s_933438.jpg", "bookUrl": "https://weread.qq.com/web/appreader/b5632b905e3e3eb56204d8f"}, {"bookId": "854816", "title": "动物园里的救世主", "author": "刘慈欣", "cover": "https://wfqqreader-1252317822.image.myqcloud.com/cover/816/854816/s_854816.jpg", "bookUrl": "https://weread.qq.com/web/appreader/61a329005d0b2061a380ef4"}, {"bookId": "29977761", "title": "阿凡提的故事（全4册）", "author": "艾克拜尔·吾拉木", "cover": "https://wfqqreader-1252317822.image.myqcloud.com/cover/761/29977761/s_29977761.jpg", "bookUrl": "https://weread.qq.com/web/appreader/e9d32e4071c96ca1e9d2f14"}, {"bookId": "531304", "title": "斑羚飞渡", "author": "沈石溪", "cover": "https://wfqqreader-1252317822.image.myqcloud.com/cover/304/531304/s_531304.jpg", "bookUrl": "https://weread.qq.com/web/appreader/a4432fc0581b68a442e930f"}, {"bookId": "932119", "title": "安徒生童话（译文名著精选）", "author": "汉斯·安徒生", "cover": "https://wfqqreader-1252317822.image.myqcloud.com/cover/119/932119/s_932119.jpg", "bookUrl": "https://weread.qq.com/web/appreader/e54327b05e3917e542da6f5"}, {"bookId": "27598694", "title": "阿雏", "author": "曹文轩", "cover": "https://wfqqreader-1252317822.image.myqcloud.com/cover/694/27598694/s_27598694.jpg", "bookUrl": "https://weread.qq.com/web/appreader/da73292071a51f66da793c9"}, {"bookId": "25658201", "title": "爱丽丝梦游仙境", "author": "刘易斯·卡罗尔", "cover": "https://wfqqreader-1252317822.image.myqcloud.com/cover/201/25658201/s_25658201.jpg", "bookUrl": "https://weread.qq.com/web/appreader/76b32cc07187835976bbced"}, {"bookId": "25721097", "title": "调皮的日子1：上（彩色注音版）", "author": "秦文君", "cover": "https://wfqqreader-1252317822.image.myqcloud.com/cover/97/25721097/s_25721097.jpg", "bookUrl": "https://weread.qq.com/web/appreader/65a32d207188790965a2083"}, {"bookId": "928915", "title": "海军陆战队2：狙击精英", "author": "八路", "cover": "https://wfqqreader-1252317822.image.myqcloud.com/cover/915/928915/s_928915.jpg", "bookUrl": "https://weread.qq.com/web/appreader/55e32cd05e2c9355ea08c10"}, {"bookId": "908203", "title": "皮皮鲁保卫叛逆者", "author": "郑渊洁", "cover": "https://wfqqreader-1252317822.image.myqcloud.com/cover/203/908203/s_908203.jpg", "bookUrl": "https://weread.qq.com/web/appreader/067328f05ddbab0670b7420"}, {"bookId": "25721097", "title": "调皮的日子1：上（彩色注音版）", "author": "秦文君", "cover": "https://wfqqreader-1252317822.image.myqcloud.com/cover/97/25721097/s_25721097.jpg", "bookUrl": "https://weread.qq.com/web/appreader/65a32d207188790965a2083"}, {"bookId": "932119", "title": "安徒生童话（译文名著精选）", "author": "汉斯·安徒生", "cover": "https://wfqqreader-1252317822.image.myqcloud.com/cover/119/932119/s_932119.jpg", "bookUrl": "https://weread.qq.com/web/appreader/e54327b05e3917e542da6f5"}, {"bookId": "25499128", "title": "耗子大爷起晚了", "author": "叶广芩", "cover": "https://wfqqreader-1252317822.image.myqcloud.com/cover/128/25499128/s_25499128.jpg", "bookUrl": "https://weread.qq.com/web/appreader/23b32b00718515f823be756"}, {"bookId": "25824414", "title": "校园三剑客：古堡奇人（经典版）", "author": "杨鹏", "cover": "https://wfqqreader-1252317822.image.myqcloud.com/cover/414/25824414/s_25824414.jpg", "bookUrl": "https://weread.qq.com/web/appreader/fd432fb0718a0c9efd405ad"}, {"bookId": "916893", "title": "影响孩子一生的101个成长故事（男孩卷）", "author": "童心", "cover": "https://wfqqreader-1252317822.image.myqcloud.com/cover/893/916893/s_916893.jpg", "bookUrl": "https://weread.qq.com/web/appreader/18932c305dfd9d189c7cb3d"}, {"bookId": "506666", "title": "婴儿早期智力开发", "author": "元秀", "cover": "https://wfqqreader-1252317822.image.myqcloud.com/cover/666/506666/s_506666.jpg", "bookUrl": "https://weread.qq.com/web/appreader/c01328e057bb2ac01077560"}, {"bookId": "531303", "title": "雪豹悲歌", "author": "沈石溪", "cover": "https://wfqqreader-1252317822.image.myqcloud.com/cover/303/531303/s_531303.jpg", "bookUrl": "https://weread.qq.com/web/appreader/c1732be0581b67c17a34f19"}, {"bookId": "922689", "title": "尼尔斯骑鹅旅行记（诺贝尔文学奖大系）", "author": "拉格洛夫", "cover": "https://wfqqreader-1252317822.image.myqcloud.com/cover/689/922689/s_922689.jpg", "bookUrl": "https://weread.qq.com/web/appreader/a65323705e1441a652bf521"}, {"bookId": "916893", "title": "影响孩子一生的101个成长故事（男孩卷）", "author": "童心", "cover": "https://wfqqreader-1252317822.image.myqcloud.com/cover/893/916893/s_916893.jpg", "bookUrl": "https://weread.qq.com/web/appreader/18932c305dfd9d189c7cb3d"}, {"bookId": "22624189", "title": "让女孩着迷的世界公主故事集（优雅卷）", "author": "花朵朵", "cover": "https://wfqqreader-1252317822.image.myqcloud.com/cover/189/22624189/s_22624189.jpg", "bookUrl": "https://weread.qq.com/web/appreader/65732d40715937bd6574447"}, {"bookId": "25499128", "title": "耗子大爷起晚了", "author": "叶广芩", "cover": "https://wfqqreader-1252317822.image.myqcloud.com/cover/128/25499128/s_25499128.jpg", "bookUrl": "https://weread.qq.com/web/appreader/23b32b00718515f823be756"}, {"bookId": "25720815", "title": "装在口袋里的爸爸·小人国来的公主（注音版）", "author": "杨鹏", "cover": "https://wfqqreader-1252317822.image.myqcloud.com/cover/815/25720815/s_25720815.jpg", "bookUrl": "https://weread.qq.com/web/appreader/f0932e10718877eff09f14d"}, {"bookId": "25720825", "title": "大个子老鼠小个子猫", "author": "周锐", "cover": "https://wfqqreader-1252317822.image.myqcloud.com/cover/825/25720825/s_25720825.jpg", "bookUrl": "https://weread.qq.com/web/appreader/e5b328d0718877f9e5b9742"}, {"bookId": "534465", "title": "同桌冤家：考试真疯狂", "author": "伍美珍", "cover": "https://wfqqreader-1252317822.image.myqcloud.com/cover/465/534465/s_534465.jpg", "bookUrl": "https://weread.qq.com/web/appreader/a0832a605827c1a0899b3ba"}, {"bookId": "928914", "title": "海军陆战队1：我是特种兵", "author": "八路", "cover": "https://wfqqreader-1252317822.image.myqcloud.com/cover/914/928914/s_928914.jpg", "bookUrl": "https://weread.qq.com/web/appreader/b93322705e2c92b9377f2de"}, {"bookId": "853975", "title": "生而为猫挺好的", "author": "猫小姐", "cover": "https://wfqqreader-1252317822.image.myqcloud.com/cover/975/853975/s_853975.jpg", "bookUrl": "https://weread.qq.com/web/appreader/40832a105d07d7408e367a9"}, {"bookId": "928944", "title": "宿舍惊魂（校园侦缉档案）", "author": "许廷旺", "cover": "https://wfqqreader-1252317822.image.myqcloud.com/cover/944/928944/s_928944.jpg", "bookUrl": "https://weread.qq.com/web/appreader/6e932d005e2cb06e950ccc3"}, {"bookId": "29973868", "title": "让女孩着迷的世界公主故事集：美德卷", "author": "花朵朵主编", "cover": "https://wfqqreader-1252317822.image.myqcloud.com/cover/868/29973868/s_29973868.jpg", "bookUrl": "https://weread.qq.com/web/appreader/6f13268071c95d6c6f17a5e"}, {"bookId": "533394", "title": "野犬女皇", "author": "沈石溪", "cover": "https://wfqqreader-1252317822.image.myqcloud.com/cover/394/533394/s_533394.jpg", "bookUrl": "https://weread.qq.com/web/appreader/109321f0582392109946840"}, {"bookId": "917535", "title": "柳林风声", "author": "肯尼斯·格雷厄姆", "cover": "https://wfqqreader-1252317822.image.myqcloud.com/cover/535/917535/s_917535.jpg", "bookUrl": "https://weread.qq.com/web/appreader/315323005e001f3153c452b"}, {"bookId": "23030811", "title": "校园三剑客·变身少年（经典版）", "author": "杨鹏", "cover": "https://wfqqreader-1252317822.image.myqcloud.com/cover/811/23030811/s_23030811.jpg", "bookUrl": "https://weread.qq.com/web/appreader/59c32e20715f6c1b59c4a20"}, {"bookId": "908205", "title": "皮皮鲁和无尾大侠", "author": "郑渊洁", "cover": "https://wfqqreader-1252317822.image.myqcloud.com/cover/205/908205/s_908205.jpg", "bookUrl": "https://weread.qq.com/web/appreader/9d0322205ddbad9d0ee9a6d"}, {"bookId": "25824394", "title": "海军陆战队10：海岛争夺战", "author": "八路", "cover": "https://wfqqreader-1252317822.image.myqcloud.com/cover/394/25824394/s_25824394.jpg", "bookUrl": "https://weread.qq.com/web/appreader/0d432860718a0c8a0d4bbee"}, {"bookId": "25824396", "title": "海军陆战队11：决战太平洋", "author": "八路", "cover": "https://wfqqreader-1252317822.image.myqcloud.com/cover/396/25824396/s_25824396.jpg", "bookUrl": "https://weread.qq.com/web/appreader/fd332030718a0c8cfd32209"}, {"bookId": "916895", "title": "影响孩子一生的101个神话故事", "author": "童心", "cover": "https://wfqqreader-1252317822.image.myqcloud.com/cover/895/916895/s_916895.jpg", "bookUrl": "https://weread.qq.com/web/appreader/fa632e605dfd9ffa6c1bcd6"}, {"bookId": "25720795", "title": "小猪唏哩呼噜：唏哩呼噜和他的弟弟（彩色注音版）", "author": "孙幼军", "cover": "https://wfqqreader-1252317822.image.myqcloud.com/cover/795/25720795/s_25720795.jpg", "bookUrl": "https://weread.qq.com/web/appreader/5be32900718877db5be33ab"}, {"bookId": "23308796", "title": "中国民间故事", "author": "曾凡跃", "cover": "https://wfqqreader-1252317822.image.myqcloud.com/cover/796/23308796/s_23308796.jpg", "bookUrl": "https://weread.qq.com/web/appreader/a0932f507163a9fca094ed8"}, {"bookId": "25720819", "title": "装在口袋里的爸爸·无敌戒指", "author": "杨鹏", "cover": "https://wfqqreader-1252317822.image.myqcloud.com/cover/819/25720819/s_25720819.jpg", "bookUrl": "https://weread.qq.com/web/appreader/2b9329f0718877f32b9377d"}, {"bookId": "25720811", "title": "装在口袋里的爸爸·万能神笔", "author": "杨鹏", "cover": "https://wfqqreader-1252317822.image.myqcloud.com/cover/811/25720811/s_25720811.jpg", "bookUrl": "https://weread.qq.com/web/appreader/17632f60718877eb1765b11"}, {"bookId": "25720795", "title": "小猪唏哩呼噜：唏哩呼噜和他的弟弟（彩色注音版）", "author": "孙幼军", "cover": "https://wfqqreader-1252317822.image.myqcloud.com/cover/795/25720795/s_25720795.jpg", "bookUrl": "https://weread.qq.com/web/appreader/5be32900718877db5be33ab"}, {"bookId": "917535", "title": "柳林风声", "author": "肯尼斯·格雷厄姆", "cover": "https://wfqqreader-1252317822.image.myqcloud.com/cover/535/917535/s_917535.jpg", "bookUrl": "https://weread.qq.com/web/appreader/315323005e001f3153c452b"}, {"bookId": "25824394", "title": "海军陆战队10：海岛争夺战", "author": "八路", "cover": "https://wfqqreader-1252317822.image.myqcloud.com/cover/394/25824394/s_25824394.jpg", "bookUrl": "https://weread.qq.com/web/appreader/0d432860718a0c8a0d4bbee"}, {"bookId": "25824396", "title": "海军陆战队11：决战太平洋", "author": "八路", "cover": "https://wfqqreader-1252317822.image.myqcloud.com/cover/396/25824396/s_25824396.jpg", "bookUrl": "https://weread.qq.com/web/appreader/fd332030718a0c8cfd32209"}, {"bookId": "839225", "title": "有情世界", "author": "丰子恺", "cover": "https://wfqqreader-1252317822.image.myqcloud.com/cover/225/839225/s_839225.jpg", "bookUrl": "https://weread.qq.com/web/appreader/027323a05cce39027d6ee57"}, {"bookId": "832458", "title": "蛇王淘金", "author": "郑渊洁", "cover": "https://wfqqreader-1252317822.image.myqcloud.com/cover/458/832458/s_832458.jpg", "bookUrl": "https://weread.qq.com/web/appreader/60d321305cb3ca60d00c081"}, {"bookId": "929723", "title": "聪明老妈笨老爸", "author": "王金平", "cover": "https://wfqqreader-1252317822.image.myqcloud.com/cover/723/929723/s_929723.jpg", "bookUrl": "https://weread.qq.com/web/appreader/931322a05e2fbb931437fb6"}, {"bookId": "159952", "title": "自然纪事·胡萝卜须", "author": "儒勒·列那尔", "cover": "https://wfqqreader-1252317822.image.myqcloud.com/cover/952/159952/s_159952.jpg", "bookUrl": "https://weread.qq.com/web/appreader/b5a32f105270d0b5abbf3e5"}, {"bookId": "929723", "title": "聪明老妈笨老爸", "author": "王金平", "cover": "https://wfqqreader-1252317822.image.myqcloud.com/cover/723/929723/s_929723.jpg", "bookUrl": "https://weread.qq.com/web/appreader/931322a05e2fbb931437fb6"}, {"bookId": "23349165", "title": "梦幻小公主·海之神族卷（9-16册）", "author": "玖金", "cover": "https://wfqqreader-1252317822.image.myqcloud.com/cover/165/23349165/s_23349165.jpg", "bookUrl": "https://weread.qq.com/web/appreader/a1c324f0716447ada1c334c"}, {"bookId": "928914", "title": "海军陆战队1：我是特种兵", "author": "八路", "cover": "https://wfqqreader-1252317822.image.myqcloud.com/cover/914/928914/s_928914.jpg", "bookUrl": "https://weread.qq.com/web/appreader/b93322705e2c92b9377f2de"}, {"bookId": "910038", "title": "第一次发现名画之美：莫奈", "author": "白白兔童书馆", "cover": "https://wfqqreader-1252317822.image.myqcloud.com/cover/38/910038/s_910038.jpg", "bookUrl": "https://weread.qq.com/web/appreader/1a632f805de2d61a645c563"}, {"bookId": "23308790", "title": "西游记", "author": "吴承恩", "cover": "https://wfqqreader-1252317822.image.myqcloud.com/cover/790/23308790/s_23308790.jpg", "bookUrl": "https://weread.qq.com/web/appreader/eec322007163a9f6eecbb13"}, {"bookId": "929137", "title": "不老泉", "author": "娜塔莉·巴比特", "cover": "https://wfqqreader-1252317822.image.myqcloud.com/cover/137/929137/s_929137.jpg", "bookUrl": "https://weread.qq.com/web/appreader/1d8327605e2d711d83b0816"}, {"bookId": "910038", "title": "第一次发现名画之美：莫奈", "author": "白白兔童书馆", "cover": "https://wfqqreader-1252317822.image.myqcloud.com/cover/38/910038/s_910038.jpg", "bookUrl": "https://weread.qq.com/web/appreader/1a632f805de2d61a645c563"}, {"bookId": "22623695", "title": "让女孩一生幸福的睡前故事：灰姑娘卷", "author": "彭凡", "cover": "https://wfqqreader-1252317822.image.myqcloud.com/cover/695/22623695/s_22623695.jpg", "bookUrl": "https://weread.qq.com/web/appreader/99932a90715935cf99905d4"}, {"bookId": "27359432", "title": "故宫里的博物学（套装全3册）", "author": "小海 夏雪著 余省 张为邦 聂璜绘", "cover": "https://wfqqreader-1252317822.image.myqcloud.com/cover/432/27359432/s_27359432.jpg", "bookUrl": "https://weread.qq.com/web/appreader/7d13206071a178c87d143f1"}, {"bookId": "25721146", "title": "装在口袋里的爸爸·我会七十二变", "author": "杨鹏", "cover": "https://wfqqreader-1252317822.image.myqcloud.com/cover/146/25721146/s_25721146.jpg", "bookUrl": "https://weread.qq.com/web/appreader/c9d320e07188793ac9d4ef8"}, {"bookId": "27001515", "title": "小巴掌童话百篇", "author": "张秋生", "cover": "https://wfqqreader-1252317822.image.myqcloud.com/cover/515/27001515/s_27001515.jpg", "bookUrl": "https://weread.qq.com/web/appreader/a7932fb0719c02aba79a695"}, {"bookId": "26924497", "title": "我的儿子皮卡：尖叫", "author": "曹文轩", "cover": "https://wfqqreader-1252317822.image.myqcloud.com/cover/497/26924497/s_26924497.jpg", "bookUrl": "https://weread.qq.com/web/appreader/c8d32ae0719ad5d1c8db17a"}, {"bookId": "22623695", "title": "让女孩一生幸福的睡前故事：灰姑娘卷", "author": "彭凡", "cover": "https://wfqqreader-1252317822.image.myqcloud.com/cover/695/22623695/s_22623695.jpg", "bookUrl": "https://weread.qq.com/web/appreader/99932a90715935cf99905d4"}, {"bookId": "180860", "title": "骑鹅旅行记", "author": "权锗云", "cover": "https://wfqqreader-1252317822.image.myqcloud.com/cover/860/180860/s_180860.jpg", "bookUrl": "https://weread.qq.com/web/appreader/c2a3251052c27cc2a0398d7"}]
